Workbook

Sheet Reminder
A1: Jenis Agenda | B1: Nama Agenda | C1: Tanggal Load | D1: DeadLine | E1: PIC | F1: Keterangan | G1: RowID | H1: status | I1: sisa hari | J1: Link File Lampiran
A2: Tugas | B2: Presentasi AKM | C2: 45787.555 | D2: 45783.5 | E2: MELLANIA PUTRI RATNAWATI | F2: 🚨🚨REMINDER AKM II🚨🚨 ⿡ Tugas Individu 1.⁠ ⁠Penyelesaian soal 2.⁠ ⁠⁠Membuat Kerangka Materi/infografis di buku/binder B5 dapat melanjutkan dr buku AKM I (bisa mulai dicicil) ⿢ Tugas Presentasi Presensi 13 s.d. 15 P16.1, P16.8, BE16.16 jurnal s.d. pembayaran 📌 Format file Word atau Excel dan PPT 📌 nama file: No. Presensi_Nama Mahasiswa_No Soal_Jenis Materi 🗓 TODAAYY 📍 LMS dan gdrive https://drive.google.com/drive/folders/16zmz1em_nsWKaNK9Zm-A8HwwGovP58gx | G2: 43aec732-f896-4112-b0bc-acd8b5d7b6e3 | H2: {=IF(I2:I958="","",IF(I2:I958>0,"Outstanding","Lewat/Selesai"))} -> Lewat/Selesai | I2: {=IF(D2:D958="","",D2:D958-today())} -> -189.5
A3: Kuis | B3: Kuis Pajak Internasional | C3: 45788.549 | D3: 45797.583 | E3: QURROTU A'YUMINA | F3: Kuis PI pertemuan 1 - pertemuan 3 | G3: 8b929640-a5a5-4ab4-908e-072520893fc3 | H3: Lewat/Selesai | I3: -175.41667
A4: Pengingat | B4: Ulang tahun AHMAD NUR WAKHID | C4: 45789.334 | D4: 45797 | E4: Sistem | F4: Selamat ulang tahun untuk AHMAD NUR WAKHID! | G4: ULTAH_AHMADNURWAKHID_2025 | H4: Lewat/Selesai | I4: -176
A5: Pengingat | B5: Ulang tahun ANISA FATMANINGTYAS | C5: 45789.334 | D5: 45892 | E5: Sistem | F5: Selamat ulang tahun untuk ANISA FATMANINGTYAS! | G5: ULTAH_ANISAFATMANINGTYAS_2025 | H5: Lewat/Selesai | I5: -81
A6: Pengingat | B6: Ulang tahun ANNISA FADILLAH HERNAWAN | C6: 45789.334 | D6: 45740 | E6: Sistem | F6: Selamat ulang tahun untuk ANNISA FADILLAH HERNAWAN! | G6: ULTAH_ANNISAFADILLAHHERNAWAN_2025 | H6: Lewat/Selesai | I6: -233
A7: Pengingat | B7: Ulang tahun ARRAZ MEIDYAN | C7: 45789.334 | D7: 45801 | E7: Sistem | F7: Selamat ulang tahun untuk ARRAZ MEIDYAN! | G7: ULTAH_ARRAZMEIDYAN_2025 | H7: Lewat/Selesai | I7: -172
A8: Pengingat | B8: Ulang tahun AYU MITHA VALLENTYA | C8: 45789.334 | D8: 45984 | E8: Sistem | F8: Selamat ulang tahun untuk AYU MITHA VALLENTYA! | G8: ULTAH_AYUMITHAVALLENTYA_2025 | H8: Outstanding | I8: 11
A9: Pengingat | B9: Ulang tahun DEA LESTI BRIANA | C9: 45789.334 | D9: 45901 | E9: Sistem | F9: Selamat ulang tahun untuk DEA LESTI BRIANA! | G9: ULTAH_DEALESTIBRIANA_2025 | H9: Lewat/Selesai | I9: -72
A11: Pengingat | B11: Ulang tahun EVI SETYANINGSIH | C11: 45789.334 | D11: 45966 | E11: Sistem | F11: Selamat ulang tahun untuk EVI SETYANINGSIH! | G11: ULTAH_EVISETYANINGSIH_2025 | H11: Lewat/Selesai | I11: -7
A12: Pengingat | B12: Ulang tahun FELITA DELVIANA YOGYANTORO | C12: 45789.334 | D12: 45714 | E12: Sistem | F12: Selamat ulang tahun untuk FELITA DELVIANA YOGYANTORO! | G12: ULTAH_FELITADELVIANAYOGYANTORO_2025 | H12: Lewat/Selesai | I12: -259
A13: Pengingat | B13: Ulang tahun GIDEON HAMONANGAN SIMANJUNTAK | C13: 45789.334 | D13: 45784 | E13: Sistem | F13: Selamat ulang tahun untuk GIDEON HAMONANGAN SIMANJUNTAK! | G13: ULTAH_GIDEONHAMONANGANSIMANJUNTAK_2025 | H13: Lewat/Selesai | I13: -189
A14: Pengingat | B14: Ulang tahun INDAH BASUKI SETIA INDRA | C14: 45789.334 | D14: 45807 | E14: Sistem | F14: Selamat ulang tahun untuk INDAH BASUKI SETIA INDRA! | G14: ULTAH_INDAHBASUKISETIAINDRA_2025 | H14: Lewat/Selesai | I14: -166
A15: Pengingat | B15: Ulang tahun MARTIN FELIX SIREGAR | C15: 45789.334 | D15: 45810 | E15: Sistem | F15: Selamat ulang tahun untuk MARTIN FELIX SIREGAR! | G15: ULTAH_MARTINFELIXSIREGAR_2025 | H15: Lewat/Selesai | I15: -163
... A30: Pengingat | B30: Ulang tahun ZETA TALADZUL AYUN | C30: 45789.334 | D30: 45664 | E30: Sistem | F30: Selamat ulang tahun untuk ZETA TALADZUL AYUN! | G30: ULTAH_ZETATALADZULAYUN_2025 | H30: Lewat/Selesai | I30: -309
A31: Tugas | B31: Tugas AKM | C31: 45791.355 | D31: 45797.999 | E31: ZETA TALADZUL AYUN | F31: ✨Tugas AKM II✨ 1️⃣ Tugas Individu 1.⁠ ⁠Penyelesaian soal (ditulis tangan) 2.⁠ ⁠⁠Membuat Kerangka materi / infografis (ringkas dan komprehensif, dalam bentuk gambar dan kata kunci) (tulis tangan, cukup 1 halaman, boleh lebih) di buku B5 dapat melanjutkan dr buku AKM I 2️⃣ Tugas Presentasi Presensi 21 s.d. 25 E18.10 + 11, E18.21, E18.23 + 24 + 25, E18.28 + 31 + jurnal + 32, P18.10 + jurnal 📌 Urutan pengerjaan •⁠ ⁠Pokok Materi •⁠ ⁠⁠Referensi, halaman, dan penjelasan (infografis, ringkas dan komprehensif, dalam bentuk bagan, tabel, dan kata kunci) •⁠ ⁠⁠Soal, data singkat, subpertanyaan, jawaban (disertai data yang diperlukan, penjelasan langkah-langkah pengerjaan soal, hitungan) •⁠ ⁠⁠Setiap subpertanyaan langsung disandingkan dengan jawaban •⁠ ⁠⁠Jumlah slide sesedikit mungkin 📌 Format file Word atau Excel dan PPT 📌 nama file: No. Presensi_Nama Mahasiswa_No Soal_Jenis Materi 🗓️ Selasa, 20 Mei 2025 📍 LMS dan gdrive https://drive.google.com/drive/folders/16zmz1em_nsWKaNK9Zm-A8HwwGovP58gx 🤺🤺🤺🤺 | G31: 82ed4bbf-9cf0-435e-97b6-e4ef7c8073bb | H31: Lewat/Selesai | I31: -175.00069 | J31: https://drive.google.com/file/d/1dPfDRHhusjnEJ2wIW2Be1vYReXbRPzO-/view?usp=drivesdk
A32: Tugas | B32: AKSK Kelompok | C32: 45792.353 | D32: 45794.749 | E32: ANISA FATMANINGTYAS | F32: 📌 Kelompok - Melengkapi tugas kelompok minggu lalu (tambahkan tabelnya) - Tugas Tambahan 1 (terlampir) - Kelompok 7 : presentasi materi Bab 7 Buku Arens ed.17 - Kelompok 1 : presentasi materi dari Buku Praktikum 1: Bagian I & II ⚠️ Pengumpulan: https://bit.ly/44_AKSK 📅 Deadline: Sabtu, 17 Mei 2025 sebelum pukul 18.00 WIB | G32: 66b8ae13-671a-484c-81a8-b3222902c9f7 | H32: Lewat/Selesai | I32: -178.25069 | J32: https://drive.google.com/file/d/1dRcZRH4s4vKNFw1rPrNQueII5REZoFpk/view?usp=drivesdk
A33: Tugas | B33: AKSK Individu | C33: 45792.424 | D33: 45794.749 | E33: DEA LESTI BRIANA | F33: 📌 Individu 1️⃣ Tugas Individu ke-5 - Resume materi Bab 7 Buku Arens ed.17 - Resume materi dari Buku Praktikum 1: Bagian I & II Ketentuan resume : - Setiap resume maksimal 2 halaman folio - Ditulis tangan di kertas ukuran folio (buku/kertas) ⚠️ Pengumpulan: https://bit.ly/44_AKSK 📅 Deadline: Sabtu, 17 Mei 2025 sebelum pukul 18.00 WIB | G33: f6460e41-2ca1-47ed-a2c3-2e01582d0d74 | H33: Lewat/Selesai | I33: -178.25069
A34: Kuis | B34: KUIS AKSK | C34: 45792.425 | D34: 45796.312 | E34: DEA LESTI BRIANA | F34: 2️⃣ Quiz: Senin, 19 Mei 2025 Materi Quiz: - Tahapan Proses Audit (fase audit) - Bab 7 Buku Arens ed.17 Closebook | G34: d5541dc9-6144-45b9-bc29-f562463dd9bb | H34: Lewat/Selesai | I34: -176.6875
A35: Tugas | B35: Komunikasi Individu | C35: 45794.517 | D35: 45798.999 | E35: EKA ADHIKARA RAHIM | F35: Latihan studi kasus individu: menyusun kata-kata efektif sesuai ppt komunikasi pertemuan 4 (terlampir) boleh ketik, disubmit di LMS (menunggu) deadline Rabu, 21 Mei 2025 | G35: 502d34c1-7a95-4afc-b9a0-baa6a6eb7b4f | H35: Lewat/Selesai | I35: -174.00069 | J35: https://drive.google.com/file/d/1TnWRVE3iOfZz0cinxHsBuNvCwhwxexLa/view?usp=drivesdk
A36: Tugas | B36: Komunikasi Kelompok | C36: 45794.523 | D36: 45798.999 | E36: EKA ADHIKARA RAHIM | F36: tugas diskusi sesuai instruksi di ppt komunikasi pertemuan 4 sesuai pembagian kelompok (terlampir) diketik disubmit di LMS (menunggu) Deadline Rabu, 21 Mei 2025 | G36: 601a8cde-0587-488f-b73f-d993fc3bc1d3 | H36: Lewat/Selesai | I36: -174.00069 | J36: https://drive.google.com/file/d/1ZysxMHLD3LAwYVLFOyVSxfOUyWLqcK-1/view?usp=drivesdk
A37: Kuis | B37: Quiz ADP | C37: 45795.891 | D37: 45796.597 | F37: Quiz ADP, 19 Mei 2025 (14.05 s.d. 14.22) | G37: 7b00ec61-d984-4c2e-9fec-e5b0e29d00c3 | H37: Lewat/Selesai | I37: -176.40278
A38: Pengingat | B38: Olahraga Bareng | C38: 45796.796 | D38: 45782.663 | F38: Kamu tahu ngga kenapa diadakan olahraga bareng? Agar kita dapat berkeringat bareng. | G38: 81058270-9714-4d29-83e0-bab6b0794d92 | H38: Lewat/Selesai | I38: -190.33681 | J38: https://drive.google.com/file/d/1PsqIcu7k6RzFScuSL7QPA3UaDO2jFVPw/view?usp=drivesdk
A39: Pengingat | B39: Apel Pagi | C39: 45796.798 | D39: 45783.26 | F39: Apel Pagi aja aku datengin, masa kamu ngga aku apelin. | G39: 5caf5f7b-4c21-4cb0-b852-992fde33cb85 | H39: Lewat/Selesai | I39: -189.73958
A40: Pengingat | B40: Olahraga Bareng | C40: 45796.799 | D40: 45796.663 | F40: Kamu tahu ngga kenapa diadakan olahraga bareng? Agar kita dapat berkeringat bareng. | G40: 02405abc-577f-4142-acb7-4a9aef24e815 | H40: Lewat/Selesai | I40: -176.33681 | J40: https://drive.google.com/file/d/17A0-Vdet25_eLdRL6kaQCYhSjh-hmtmv/view?usp=drivesdk
A41: Pengingat | B41: Upacara Bendera | C41: 45796.8 | D41: 45796.26 | F41: Jangan hanya mantan aja yang kita kenang, tapi para pahlawan juga wajib kita kenang. Ayo kita Upacara. | G41: 3a03542f-a604-4684-923c-1c2a6d4759c0 | H41: Lewat/Selesai | I41: -176.73958
A42: Pengingat | B42: Apel Pagi | C42: 45796.8 | D42: 45797.26 | F42: Apel Pagi aja aku datengin, masa kamu ngga aku apelin. | G42: 04e6ce0a-adb7-4ea0-84b6-570c106924dd | H42: Lewat/Selesai | I42: -175.73958
A43: Pengingat | B43: Bonding Angkatan | C43: 45796.802 | D43: 45800.302 | F43: Datang aja dulu, mana tau jodohnya ketemu disana. | G43: e705c0e1-ea7d-4ab1-ba05-d33483b8a262 | H43: Lewat/Selesai | I43: -172.69792
A44: Pengingat | B44: Olahraga Bareng | C44: 45796.803 | D44: 45803.663 | F44: Kamu tahu ngga kenapa diadakan olahraga bareng? Agar kita dapat berkeringat bareng. | G44: 93059e6f-c86a-4959-aa72-a0a148789530 | H44: Lewat/Selesai | I44: -169.33681 | J44: https://drive.google.com/file/d/1YmjYjLPgeYPaWn4G3PK8IKyOujSqpPPy/view?usp=drivesdk
A45: Pengingat | B45: Apel Pagi | C45: 45796.803 | D45: 45804.26 | F45: Apel Pagi aja aku datengin, masa kamu ngga aku apelin. | G45: fff80feb-a5f7-4f62-a28f-45ac1d157da6 | H45: Lewat/Selesai | I45: -168.73958
A46: Tugas | B46: AKSK Kelompok | C46: 45797.813 | D46: 45801.749 | E46: ANISA FATMANINGTYAS | F46: Presentasi Kelompok - Kelompok 1: Praktikum Bagian 1&2 - Kelompok 2: Bab 8 ed.17 - Kelompok 3: Bab 9 ed.17 file presentasi dikumpulkan di https://bit.ly/44_AKSK Paling lambat Sabtu, 24 Mei sebelum pukul 18.00 WIB | G46: 65c73fb5-f3f6-48f5-8eb4-60055758cc9a | H46: Lewat/Selesai | I46: -171.25069
A47: Tugas | B47: Presentasi Mankeu | C47: 45798.395 | D47: 45799.5 | E47: YOHANA ESTERINDAH SIMANJUNTAK | F47: ❗MANKEU❗pertemuan 5 : Bab 9 penentuan nilai obligasi testi dari senior : 1. kalo bisa jelasin minimal spt video bapaknya di https://youtu.be/kvuYk6O5PxY?si=FOk3ohHAhcIhGpSo 2. ⁠paham dan menguasai materi sampe ke inti2nya 3. ⁠awal ngomong jgn hah hoh hah hoh, harus terlihat paham. karena kalo tau awal2 udah kebingungan pasti ga belajar 4. ⁠usahain pas menjelaskan materi minimal 10 menit 5. ⁠boleh buka PPT, notes, hp ke depan 6. ⁠usahain belajar PPT bapaknya dulu baru zoom untuk diskusi bareng2 sama kelompoknya masing2 | G47: e150ffea-905a-49dd-9c3b-616affed9677 | H47: Lewat/Selesai | I47: -173.5
A48: Tugas | B48: Pelajari materi PI pertemuan 5 + jawan kasus diskusi PT Madania | C48: 45798.631 | D48: 45799.58 | E48: QURROTU A'YUMINA | F48: Pelajari materi PI pertemuan 5 + jawan kasus diskusi PT Madania. File terlampir | G48: 221becaf-0c08-4c22-b274-04e9be02b29d | H48: Lewat/Selesai | I48: -173.42014 | J48: https://drive.google.com/file/d/1vNxY1ijZPuuUc-ydXIEZqDnqW5QOOgHD/view?usp=drivesdk
A49: Tugas | B49: Pelajari materi PI pertemuan 5 + jawan kasus diskusi PT Madania. | C49: 45798.632 | D49: 45799.583 | E49: QURROTU A'YUMINA | F49: Pelajari materi PI pertemuan 5 + jawan kasus diskusi PT Madania. File terlampir | G49: a65cd764-5384-45b4-b9ad-ec2c5f68894e | H49: Lewat/Selesai | I49: -173.41667 | J49: https://drive.google.com/file/d/1MmovnOKCNvdIj-YjFXFztkegLR84FnZK/view?usp=drivesdk
A50: Pengingat | B50: Isi Data Lokasi Visit (Probis WP) | C50: 45799.566 | D50: 45799.999 | E50: EVI SETYANINGSIH | F50: ✨Proses Bisnis WP✨ Buat penerbitan Surat Izin Visit Lokasi Usaha, minta tolong diisi yaa di tautan berikut: https://drive.google.com/drive/u/0/mobile/folders/1X6tGt-ogChS32F_zfjJIHG-Wx-K9ztHX/1zx_VfTXXmG43wBldRAWeZNr9J_kwNqyB/1C6mF-IqewzO7Cy_TP7RXSEDDaNchv6Th/12kA01B3N5HV0je53rCAYHDmmJNgMNOr1?usp=sharing&sort=13&direction=a Paling lambat: Hari ini jam 23.59, soalnya mau segera diajuin 🙏 Terima kasih | G50: 18435a85-d116-4f86-9995-92bd04578bdd | H50: Lewat/Selesai | I50: -173.00069
A51: Tugas | B51: Tugas AKM II | C51: 45799.587 | D51: 45804.999 | E51: ZETA TALADZUL AYUN | F51: ✨Tugas AKM II✨ Tugas Presentasi Presensi 26 s.d. 4 Akuntansi Syariah (Sesuai Word Tugas Terlampir) 📌 (Referensi OJK download dari LMS) Jelaskan •⁠ ⁠jenis pembiayaan, penjelasan •⁠ ⁠skema pembiayaan •⁠ ⁠contoh kasus •⁠ ⁠perhitungan •⁠ ⁠tabel •⁠ ⁠jurnal: Akun dalam bahasa indonesia (ikuti di modul), disampingnya ditulis juga nama akun dalam bahasa inggris. Untuk pembiayaan murabahah, sertakan pembukuan pelunasan utang murabahah sebelum jatuh tempo (pupmsjt) 📌 Format file Word atau Excel dan PPT 📌 nama file: No. Presensi_Nama Mahasiswa_No Soal_Jenis Materi 🗓️ Selasa, 27 Mei 2025 📍 LMS dan gdrive https://drive.google.com/drive/folders/16zmz1em_nsWKaNK9Zm-A8HwwGovP58gx 🤺🤺🤺🤺 | G51: cd629b31-10f5-4302-8608-6368462aa49f | H51: Lewat/Selesai | I51: -168.00069 | J51: https://docs.google.com/document/d/16yaJm23WSWIVwrD15ZPi9eaIicSw7Xn2/edit?usp=drivesdk&ouid=110346958639123070701&rtpof=true&sd=true
A52: Tugas | B52: Presentasi Mankeu | C52: 45799.839 | D52: 45805.5 | E52: YOHANA ESTERINDAH SIMANJUNTAK | F52: ❗MANKEU❗pertemuan 6 : Bab 10 penentuan nilai saham testi dari senior : 1. kalo bisa jelasin minimal spt video bapaknya di https://youtu.be/C0JZTvN_ePc?si=WX3GH_0DKeolsgSD 2. ⁠paham dan menguasai materi sampe ke inti2nya di tiap slide 3. ⁠awal ngomong jgn hah hoh hah hoh, harus terlihat paham. karena kalo tau awal2 udah kebingungan pasti ga belajar 4. ⁠usahain pas menjelaskan materi maks 8-10 menit, kalo dah 4 menit dah aman sebenernya 5. ⁠boleh buka PPT, notes, hp ke depan 6. ⁠usahain belajar PPT bapaknya dulu baru zoom untuk diskusi bareng2 sama kelompoknya masing2 | G52: 2a964ec6-1b93-45c9-aa3c-73927559586b | H52: Lewat/Selesai | I52: -167.5
A53: Tugas | B53: Deadline Pengumpulan Laporan Visit Proses Bisnis | C53: 45800.576 | D53: 45811.958 | E53: EVI SETYANINGSIH | F53: Tugas Proses Bisnis Wajib Pajak 👨‍🏭 Tiap kelompok melakukan kunjungan pada obyek pembelajaran (studi tour) dengan berfokus pada pendeskripsian proses bisnis obyek visitasi. Uraian Tugas: - Tiap kelompok menyusun daftar pertanyaan untuk mempelajari proses bisnis, bukan dalam rangka penggalian potensi. Sehingga tidak diperkenankan menanyakan omset, biaya, dst. - Masing-masing kelompok mendokumentasikan aktivitas kunjungan dalam bentuk tulisan, audio, video. - Masing-masing kelompok menuangkan dokumentasi dalam bentuk Tulisan (PPT) dan Presentasi (PPT dan sejenisnya). Jadi, hasil yang dikumpulkan: laporan kegiatan hasil kunjungan, Power Point (PPT), dan video dokumentasi Di dalam laporan dan PPT ada diagram proses bisnis usaha yang diamati (BPMN/Flowchart) Surat izin sedang dalam proses, jika sudah ditandatangani akan disampaikan kemudian. ⚠️ DL: Selasa, 3 June 2025, 23.59 Kriteria Penilaian: ● Kemampuan menangkap fenomena dalam proses bisnis yang diamati. ● Kemampuan mengidentifikasi komponen model bisnis. ● Kemampuan teknis proses bisnis. ● Kemampuan menuangkan dalam bentuk tulisan dan presentasi terstruktur. ● Kebenaran pemilihan simbol dalam menggambarkan proses atau bagian proses. ● Semakin tajam komentar/analisis semakin baik. ● Pengerjaan tugas yang terindikasi menyalin tugas teman, tidak diberikan nilai. | G53: a54c03f9-bcad-4c97-bc94-d5872614fae8 | H53: Lewat/Selesai | I53: -161.04236 | J53: https://docs.google.com/document/d/1Uz_oFHzYVq1t2XytiPq_KzrG_9xjgRIW/edit?usp=drivesdk&ouid=110346958639123070701&rtpof=true&sd=true
A54: Tugas | B54: Kuis Pajak Internasional | C54: 45800.74 | D54: 45804.583 | E54: QURROTU A'YUMINA | F54: Kuis Pajak Internasional materi pertemuan 4,5,6 Pelajari materi pertemuan 6 Usahakan aktif di kelas ya, boleh tanya atau jawab, semangatttt | G54: 3609f96b-9676-44ee-89e4-f912e4cb3229 | H54: Lewat/Selesai | I54: -168.41667 | J54: https://drive.google.com/file/d/1ldmAy2VK162oKZI7AUe7XNttEpNnd1FC/view?usp=drivesdk
A55: Tugas | B55: Tugas Komunikasi: Transkrip Roleplay Menjawab Telepon | C55: 45803.267 | D55: 45805.5 | E55: EKA ADHIKARA RAHIM | F55: ketik, upload di LMS | G55: 2293f9ab-1a4a-4842-a217-480e29246154 | H55: Lewat/Selesai | I55: -167.5 | J55: https://drive.google.com/file/d/10p_M6pT_A9mrRKWdDfuaOuwdUQ3g0CwC/view?usp=drivesdk
A56: Tugas | B56: Tugas Komunikasi: Tugas Konsep ND | C56: 45803.268 | D56: 45805.5 | E56: EKA ADHIKARA RAHIM | F56: Kerjakan tugas di halaman terakhir PPT pertemuan 5! | G56: c73ceefe-7ee7-4284-9cd7-4f715df01c56 | H56: Lewat/Selesai | I56: -167.5 | J56: https://drive.google.com/file/d/1RoHxnag0Ggx19C14YssLWtewNq1usoHs/view?usp=drivesdk
A57: Kuis | B57: Kuis Pajak Internasional | C57: 45805.343 | D57: 45811.583 | E57: QURROTU A'YUMINA | F57: Kuis Pajak Internasional pertemuan 1-6, soal pilgan, materi bisa dilihat di link drive kelas yaa. Selamat belajar https://drive.google.com/drive/folders/1K1PpoVr0EzIT3GiJBmkcgYABR6ct3Ec_ | G57: 17bec10a-06b4-4573-ae4f-8dec971896b3 | H57: Lewat/Selesai | I57: -161.41667
A58: Tugas | B58: AKSK KELOMPOK | C58: 45805.355 | D58: 45808.749 | E58: ANISA FATMANINGTYAS | F58: Presentasi Kelompok - Kelompok 4: Bab 10 Arens ed.17 - Kelompok 5: Bab 11 Arens ed.17 file presentasi dikumpulkan di https://bit.ly/44_AKSK Paling lambat Sabtu, 31 Mei sebelum pukul 18.00 WIB | G58: 433755e8-edcf-4777-a7cc-eaf0d9a0cf7c | H58: Lewat/Selesai | I58: -164.25069
A59: Tugas | B59: Tugas Kelompok Ke 2 dan 3 ADP | C59: 45807.661 | D59: 45809.958 | E59: AHMAD NUR WAKHID | F59: 🚨🚨TUGAS ANALITIKA DATA PERPAJAKAN🚨🚨 Berikut pengumuman terkait Tugas Kelompok mata kuliah Analitika Data Perpajakan: - Tugas Ke 2 (Pertemuan 4) Klasterisasi, Deadline Minggu, 1 Juni 2025 23.59 WIB - Tugas Ke 3 (Pertemuan 5) Klasifikasi, Deadline Minggu, 1 Juni 2025 23.59 WIB 🏋‍♀Ketentuan Pengumpulan Tugas: Data yang dianalisis: - Bisa berupa data non-perpajakan, namun disarankan menggunakan data perpajakan untuk hasil yang lebih relevan (Nilai tugas akan lebih tinggi jika menggunakan data perpajakan dan jumlah baris data lebih dari 500 baris). - Boleh menggunakan data sebelumnya (Tugas 1) atau bisa pake data baru Kerahasiaan Data: - Jika data mengandung informasi rahasia (Nama Wajib Pajak, NPWP, dll.), wajib disamarkan untuk menjaga privasi. Format Laporan: a. Permasalahan b. Eksplorasi Data c. Pemilihan Model d. Hasil e. Evaluasi model f. Interpretasi hasil g. Kesimpulan Referensi dapat dilihat di Folder Pak Galela Pertemuan 5 dan 6 Format Penamaan File Tugas: 1. Data Excel: (.xlsx atau .csv) contoh: 4-4_Kelompok 1_Tugas Ke-3 Klasifikasi_Pertemuan 5.xlsx 2. File Orange: (.ows) contoh: 4-4_Kelompok 1_Tugas Ke-3 Klasifikasi_Pertemuan 5.ows 3. Laporan Hasil Analisis: (.pdf) contoh: 4-4_Kelompok 1_Tugas Ke-3 Klasifikasi_Pertemuan 5.pdf (Tidak perlu di zip, langsung diupload di folder kelompok masing-masing) 📍Link Pengumpulan Tugas: [Link Pengumpulan Tugas: https://drive.google.com/open?id=1DkQP4AZWubhDITHd1ZXpblnrrWJ81G-5&usp=drive_fs ] | G59: 665e88bf-f9d2-4577-99fc-821df61a3207 | H59: Lewat/Selesai | I59: -163.04236 | J59: https://drive.google.com/file/d/1k2P2366NykznVmnFsWDacUe_OT5dMOck/view?usp=drivesdk
A60: Tugas | B60: Presentasi Mankeu | C60: 45807.833 | D60: 45813.5 | E60: YOHANA ESTERINDAH SIMANJUNTAK | F60: ❗MANKEU❗pertemuan 7 : Bab 11 Kriteria Pengambilan Keputusan Investasi testi dari senior : 1. kalo bisa jelasin minimal spt video bapaknya di https://youtu.be/QmLLLpzlB4U?si=XOp_HWKz7tnPX2go 2. ⁠paham dan menguasai materi sampe ke inti2nya di tiap slide 3. ⁠awal ngomong jgn hah hoh hah hoh, harus terlihat paham. karena kalo tau awal2 udah kebingungan pasti ga belajar 4. ⁠usahain pas menjelaskan materi maks 8-10 menit, kalo dah 4 menit dah aman sebenernya 5. ⁠boleh buka PPT, notes, hp ke depan 6. ⁠usahain belajar PPT bapaknya dulu baru zoom untuk diskusi bareng2 sama kelompoknya masing2 | G60: db5f2750-26d1-40c4-b6a7-0008b6f07e08 | H60: Lewat/Selesai | I60: -159.5
A61: Tugas | B61: TUGAS AKM II | C61: 45809.931 | D61: 45811.999 | E61: ZETA TALADZUL AYUN | F61: ✨Tugas AKM II✨ Tugas Individu (Penyelesaian Soal & Infografis) dikumpulkan! Tugas Presentasi Pesensi 3 s.d. 4 (melanjutkan presentasi) Presensi 5 Akuntansi Syariah Pembiayaan Mudarabah 📌 (Referensi OJK terlampir) Jelaskan •⁠ ⁠jenis pembiayaan, penjelasan •⁠ ⁠skema pembiayaan •⁠ ⁠contoh kasus •⁠ ⁠perhitungan •⁠ ⁠tabel •⁠ ⁠jurnal: Akun dalam bahasa indonesia (ikuti di modul), disampingnya ditulis juga nama akun dalam bahasa inggris. 📌 Format file Word atau Excel dan PPT 📌 nama file: No. Presensi_Nama Mahasiswa_No Soal_Jenis Materi 🗓️ Selasa, 3 Juni 2025 📍 LMS dan gdrive https://drive.google.com/drive/folders/16zmz1em_nsWKaNK9Zm-A8HwwGovP58gx 🤺🤺🤺🤺 | G61: ea8e7dcb-b58c-40ff-9d5c-b2b2e43a5d36 | H61: Lewat/Selesai | I61: -161.00069 | J61: https://drive.google.com/file/d/1yr61DXxIbbdyHjulcrWxRvL0BOe7ZbZe/view?usp=drivesdk
A62: Kuis | B62: KUIS: Komunikasi Perpajakan | C62: 45811.499 | D62: 45813.438 | E62: EKA ADHIKARA RAHIM | F62: kuis komunikasi perpajakan materi sebelum UTS, semangat | G62: 8e13a89e-f5f9-4c90-92c3-dbdb1d3d827a | H62: Lewat/Selesai | I62: -159.5625
A63: Tugas | B63: Presentasi Mankeu | C63: 45813.46 | D63: 45848.5 | E63: YOHANA ESTERINDAH SIMANJUNTAK | F63: ❗MANKEU❗pertemuan 9 : Bab 13 Analisis Risiko dan Evaluasi Proyek 1. kalo bisa jelasin minimal spt video bapaknya di https://www.youtube.com/watch?v=vzodECWNm5k&list=PLRNfI9HLyZb8E4EWPl5NApDzkr7QfQwJH&index=15 2. ⁠paham dan menguasai materi sampe ke inti2nya di tiap slide 3. ⁠awal ngomong jgn hah hoh hah hoh, harus terlihat paham. karena kalo tau awal2 udah kebingungan pasti ga belajar 4. ⁠usahain pas menjelaskan materi maks 8-10 menit, kalo dah 4 menit dah aman sebenernya 5. ⁠boleh buka PPT, notes, hp ke depan 6. ⁠usahain belajar PPT bapaknya dulu baru zoom untuk diskusi bareng2 sama kelompoknya masing2 | G63: 7fccc417-6009-4f65-ab3f-6ce408b5f4a1 | H63: Lewat/Selesai | I63: -124.5
A64: Tugas | B64: Presentasi Mankeu | C64: 45813.461 | D64: 45841.5 | E64: YOHANA ESTERINDAH SIMANJUNTAK | F64: ❗MANKEU❗pertemuan 8 : Bab 12 Analisis Arus Kas Proyek testi dari senior : 1. kalo bisa jelasin minimal spt video bapaknya di https://www.youtube.com/watch?v=qeoW3j7oMW4&list=PLRNfI9HLyZb8E4EWPl5NApDzkr7QfQwJH&index=11 2. ⁠paham dan menguasai materi sampe ke inti2nya di tiap slide 3. ⁠awal ngomong jgn hah hoh hah hoh, harus terlihat paham. karena kalo tau awal2 udah kebingungan pasti ga belajar 4. ⁠usahain pas menjelaskan materi maks 8-10 menit, kalo dah 4 menit dah aman sebenernya 5. ⁠boleh buka PPT, notes, hp ke depan 6. ⁠usahain belajar PPT bapaknya dulu baru zoom untuk diskusi bareng2 sama kelompoknya masing2 | G64: b4475269-32ff-43da-9975-c942b4531f94 | H64: Lewat/Selesai | I64: -131.5
A65: Tugas | B65: Tugas ADP Ke 4 Regresi | C65: 45815.375 | D65: 45823.999 | E65: AHMAD NUR WAKHID | F65: 🚨🚨TUGAS ANALITIKA DATA PERPAJAKAN🚨🚨 Berikut pengumuman terkait Tugas Kelompok mata kuliah Analitika Data Perpajakan: - Tugas Ke 4 (Pertemuan 6) Regresi, Deadline Minggu, 15 Juni 2025 23.59 WIB Data yang dianalisis: - Bisa berupa data non-perpajakan, namun disarankan menggunakan data perpajakan untuk hasil yang lebih relevan (Nilai tugas akan lebih tinggi jika menggunakan data perpajakan dan jumlah baris data lebih dari 500 baris). - Boleh menggunakan data sebelumnya (Tugas 1) atau bisa pake data baru Kerahasiaan Data: - Jika data mengandung informasi rahasia (Nama Wajib Pajak, NPWP, dll.), wajib disamarkan untuk menjaga privasi. Format Laporan: a. Permasalahan b. Eksplorasi Data c. Pemilihan Model d. Hasil e. Evaluasi model f. Interpretasi hasil g. Kesimpulan Referensi dapat dilihat di Folder Pak Galela Pertemuan 7 Format Penamaan File Tugas: 1. Data Excel: (.xlsx atau .csv) contoh: 4-4_Kelompok 1_Tugas Ke-4 Regresi_Pertemuan 6.xlsx 2. File Orange: (.ows) contoh: 4-4_Kelompok 1_4-4_Kelompok 1_Tugas Ke-4 Regresi_Pertemuan 6.ows 3. Laporan Hasil Analisis: (.pdf) contoh: 4-4_Kelompok 1_Tugas Ke-4 Regresi_Pertemuan 6.pdf (Tidak perlu di zip, langsung diupload di folder kelompok masing-masing) 📍Link Pengumpulan Tugas: [Link Pengumpulan Tugas: https://drive.google.com/open?id=1DkQP4AZWubhDITHd1ZXpblnrrWJ81G-5&usp=drive_fs ] | G65: f7d77b56-d390-4f55-a0d9-26c0586ea83a | H65: Lewat/Selesai | I65: -149.00069
A66: Tugas | B66: AKSK KELOMPOK | C66: 45835.482 | D66: 45837.999 | E66: ANISA FATMANINGTYAS | F66: DL: Senin, 30 Juni 2025 (sebelum kelas) | G66: b2d38c58-1198-4b60-8c10-a5c82724ec3f | H66: Lewat/Selesai | I66: -135.00069 | J66: https://drive.google.com/file/d/1VCn3D6mtmQOVf7tXia4e0ER-ndmU53d2/view?usp=drivesdk
A67: Tugas | B67: Tugas Public Speaking | C67: 45835.699 | D67: 45840.999 | E67: EKA ADHIKARA RAHIM | F67: 1. Pilihlah satu topik yang kamu senangi dan ingin bagikan kepada teman-teman. Topik bebas (selain perpajakan). 2. Siapkan slide presentasi, dengan ketentuan: • halaman pertama berisi judul, nama, kelas, dan nomor urut • tidak ada batasan jumlah halaman, namun slide dipersiapkan untuk berbicara dalam waktu 7-10 menit • boleh menggunakan template dan animasi • gunakan panduan membuat slide presentasi seperti yang telah diajarkan • dapat dibuat menggunakan aplikasi Ms powerpoint, canva, prezi atau aplikasi presentasi online lainnya. 3. Slide dikumpulkan di Assignment LMS dalam bentuk PDF atau tautan/link (jika menggunakan aplikasi online). | G67: 139b830b-b1b8-4b8a-bd07-93baa6643819 | H67: Lewat/Selesai | I67: -132.00069 | J67: https://drive.google.com/file/d/18adt1oeGN__fIOXcx6HkXQW6K5aIqG3a/view?usp=drivesdk
A68: Pengingat | B68: Olahraga Bareng | C68: 45837.845 | D68: 45838.663 | F68: Kamu tahu ngga kenapa diadakan olahraga bareng? Agar kita dapat berkeringat bareng. | G68: 10647fba-8de5-4de9-9c60-c1233aa5bebb | H68: Lewat/Selesai | I68: -134.33681 | J68: https://drive.google.com/file/d/16j6jjacEEXpTFNK28yQjFGnwxtGWm2Dt/view?usp=drivesdk
A69: Pengingat | B69: Apel Pagi | C69: 45838.797 | D69: 45839.26 | F69: Apel Pagi aja aku datengin, masa kamu ngga aku apelin. | G69: b46ef3d2-1c3a-4b21-8dd5-6465fcc6e73f | H69: Lewat/Selesai | I69: -133.73958
A70: Tugas | B70: AKSK Individu | C70: 45838.876 | D70: 45843.749 | E70: ANISA FATMANINGTYAS | F70: 1. Tugas Individu ke-6 - Resume materi BIRU (liat lampiran) 2. Tugas Individu ke-7 - Resume materi PINK (liat lampiran) Ketentuan resume : - Setiap tugas resume maksimal 2 halaman folio - Ditulis tangan di kertas ukuran folio (buku/kertas) 3. Tugas Individu ke-8 - Tulis tangan kertas kerja (tugas modul 1-2 buku 1) - Format excel kertas kerja kosongan boleh diprint 4. Tugas Individu ke-9 - Tulis tangan kertas kerja (tugas modul 3 buku 1) - Format excel kertas kerja kosongan boleh diprint ⚠ Pengumpulan: https://bit.ly/44_AKSK 📅 Deadline: Sabtu, 5 Juli 2025 sebelum pukul 18.00 WIB | G70: 17a21b71-2d18-4107-b705-8db691178e28 | H70: Lewat/Selesai | I70: -129.25069 | J70: https://drive.google.com/file/d/1Pml9WhO3KnyodgFsjFzaEF6wqQ4bCKIs/view?usp=drivesdk
A71: Tugas | B71: AKSK Kelompok | C71: 45838.877 | D71: 45843.749 | E71: DEA LESTI BRIANA | F71: Tugas Kelompok - Semua Kelompok: mengerjakan tugas modul 3 buku 1 - Kelompok 2 : maju presentasi tugas modul 2 buku 1 - Kelompok 3 : maju presentasi tugas modul 3 buku 1 ⚠ Pengumpulan: https://bit.ly/44_AKSK 📅 Deadline: Sabtu, 5 Juli 2025 sebelum pukul 18.00 WIB | G71: a38dcf50-1869-488b-9575-15cd023a2e28 | H71: Lewat/Selesai | I71: -129.25069
A72: Tugas | B72: Presentasi Mankeu | C72: 45839.838 | D72: 45855.5 | E72: YOHANA ESTERINDAH SIMANJUNTAK | F72: ❗MANKEU❗pertemuan 10 : Bab 14 Biaya Modal 1. kalo bisa jelasin minimal spt video bapaknya di https://www.youtube.com/watch?v=OS5aKBJrgfc&list=PLRNfI9HLyZb8E4EWPl5NApDzkr7QfQwJH&index=12 2. ⁠paham dan menguasai materi sampe ke inti2nya di tiap slide 3. ⁠awal ngomong jgn hah hoh hah hoh, harus terlihat paham. karena kalo tau awal2 udah kebingungan pasti ga belajar 4. ⁠usahain pas menjelaskan materi maks 8-10 menit, kalo dah 4 menit dah aman sebenernya 5. ⁠boleh buka PPT, notes, hp ke depan 6. ⁠usahain belajar PPT bapaknya dulu baru zoom untuk diskusi bareng2 sama kelompoknya masing2 | G72: 83379eb3-4cd2-40b0-8440-3725137b92c1 | H72: Lewat/Selesai | I72: -117.5
A73: Tugas | B73: Presentasi Mankeu | C73: 45839.841 | D73: 45862.5 | E73: YOHANA ESTERINDAH SIMANJUNTAK | F73: ❗MANKEU❗pertemuan 11 : Bab 15 Kebijakan Struktur ModaL & Bab 16 Kebijakan Dividen 1. kalo bisa jelasin minimal spt video bapaknya di https://www.youtube.com/watch?v=vzodECWNm5k&list=PLRNfI9HLyZb8E4EWPl5NApDzkr7QfQwJH&index=15 & https://www.youtube.com/watch?v=UVpC7ZmSIUs&list=PLRNfI9HLyZb8E4EWPl5NApDzkr7QfQwJH&index=16 2. ⁠paham dan menguasai materi sampe ke inti2nya di tiap slide 3. ⁠awal ngomong jgn hah hoh hah hoh, harus terlihat paham. karena kalo tau awal2 udah kebingungan pasti ga belajar 4. ⁠usahain pas menjelaskan materi maks 8-10 menit, kalo dah 4 menit dah aman sebenernya 5. ⁠boleh buka PPT, notes, hp ke depan 6. ⁠usahain belajar PPT bapaknya dulu baru zoom untuk diskusi bareng2 sama kelompoknya masing2 | G73: 86ba82d8-b925-4211-880b-71a8cc088fd8 | H73: Lewat/Selesai | I73: -110.5
A74: Tugas | B74: Presentasi Mankeu | C74: 45839.842 | D74: 45869.5 | E74: YOHANA ESTERINDAH SIMANJUNTAK | F74: ❗MANKEU❗pertemuan 12 : Bab 17 Peramalan dan Perencanaan Keuangan 1. kalo bisa jelasin minimal spt video bapaknya di https://www.youtube.com/watch?v=rWdRDEeDu10&list=PLRNfI9HLyZb8E4EWPl5NApDzkr7QfQwJH&index=17 2. ⁠paham dan menguasai materi sampe ke inti2nya di tiap slide 3. ⁠awal ngomong jgn hah hoh hah hoh, harus terlihat paham. karena kalo tau awal2 udah kebingungan pasti ga belajar 4. ⁠usahain pas menjelaskan materi maks 8-10 menit, kalo dah 4 menit dah aman sebenernya 5. ⁠boleh buka PPT, notes, hp ke depan 6. ⁠usahain belajar PPT bapaknya dulu baru zoom untuk diskusi bareng2 sama kelompoknya masing2 | G74: 8049de7b-0d10-415b-b58c-d5e3098993e4 | H74: Lewat/Selesai | I74: -103.5
A75: Tugas | B75: Presentasi Mankeu | C75: 45839.843 | D75: 45876.5 | E75: YOHANA ESTERINDAH SIMANJUNTAK | F75: ❗MANKEU❗pertemuan 13 : Bab 18 Manajemen Modal Kerja 1. kalo bisa jelasin minimal spt video bapaknya di https://www.youtube.com/watch?v=UHVO0p6kFX8&list=PLRNfI9HLyZb8E4EWPl5NApDzkr7QfQwJH&index=14 2. ⁠paham dan menguasai materi sampe ke inti2nya di tiap slide 3. ⁠awal ngomong jgn hah hoh hah hoh, harus terlihat paham. karena kalo tau awal2 udah kebingungan pasti ga belajar 4. ⁠usahain pas menjelaskan materi maks 8-10 menit, kalo dah 4 menit dah aman sebenernya 5. ⁠boleh buka PPT, notes, hp ke depan 6. ⁠usahain belajar PPT bapaknya dulu baru zoom untuk diskusi bareng2 sama kelompoknya masing2 | G75: 939df436-a91f-4652-854e-792d55792b27 | H75: Lewat/Selesai | I75: -96.5
A76: Tugas | B76: Tugas Probis WP | C76: 45840.591 | D76: 45846.958 | E76: EVI SETYANINGSIH | F76: Buatlah update regulasi terkait ekonomi digital (termasuk peraturan-peraturan yang ada di PPT Pertemuan ke-8, terlampir.) Buatlah update regulasi terdiri dari: - Regulasi secara umum (OJK dll) - Regulasi terkait perpajakan Kalau bisa jawabannya yang panjang ya, bu Endah ga suka jawaban pendek. Dikumpulkan paling lambat hari Selasa tanggal 8 Juli 2025 Pukul 23:59 dalam format PDF/Word Submit LMS Notes dari PIC : Update semua peraturan-peraturan di PPT Pertemuan ke-9. Ceritakan peraturan-peraturan yang sudah berubah, lebih bagus ada lini masa perubahan PER/PMK/PP nya, jelasin yg detail dan banyak aja deh. Jangan singkat jawabannya, soalnya bu Endah suka jawaban yg panjang 👍 Tugas boleh dikumpulkan dalam format word/pdf | G76: 949e625c-72e2-493d-a005-49399ec2c8d1 | H76: Lewat/Selesai | I76: -126.04236 | J76: https://drive.google.com/file/d/1uE--LTKeY1yMf9--qXRy7BFWUAHvr8Ns/view?usp=drivesdk
A77: Pengingat | B77: Kerja Bakti | C77: 45841.875 | D77: 45842.667 | F77: Community Service (also known as 'Kerja Bakti') 🗓️ Friday, 04 July 2025 🕓 16.00 till 17.00 Western Indonesia Time 📍 (attached, check by full name) 'Pelopor Kebaikan' can make mistakes. Check the attached link. See https://bit.ly/Kerjabaktidansortirsampah_Penumbuhan | G77: e422aff1-cd0b-4c81-9c1e-20995eda2ff7 | H77: Lewat/Selesai | I77: -130.33333
A78: Tugas | B78: Tugas AKM II | C78: 45842.984 | D78: 45846.958 | E78: ZETA TALADZUL AYUN | F78: ✨Tugas AKM II✨ 1️⃣ Tugas Individu 1.⁠ ⁠Penyelesaian soal (ditulis tangan) 2.⁠ ⁠⁠Membuat Kerangka materi / infografis (ringkas dan komprehensif, dalam bentuk gambar dan kata kunci) (tulis tangan, cukup 1 halaman, boleh lebih) di buku B5 dapat melanjutkan dr buku AKM I 2️⃣ Tugas Presentasi Presensi 5 s.d. 11 (Soal Pertemuan 10) 📌 Urutan pengerjaan •⁠ ⁠Pokok Materi •⁠ ⁠⁠Referensi, halaman, dan penjelasan (infografis, ringkas dan komprehensif, dalam bentuk bagan, tabel, dan kata kunci) •⁠ ⁠⁠Soal, data singkat, subpertanyaan, jawaban (disertai data yang diperlukan, penjelasan langkah-langkah pengerjaan soal, hitungan) •⁠ ⁠⁠Setiap subpertanyaan langsung disandingkan dengan jawaban •⁠ ⁠⁠Jumlah slide sesedikit mungkin 📌 Format file Word atau Excel dan PPT 📌 nama file: No. Presensi_Nama Mahasiswa_No Soal_Jenis Materi 🗓️ Selasa, 8 Mei 2025 📍 LMS dan gdrive https://drive.google.com/drive/folders/1EfxeoDokR5GHJIEZU3oWr2AlEPJGT_L_ 🤺🤺🤺🤺 | G78: 82b02a6f-8822-4d8d-ac21-d548abd524ee | H78: Lewat/Selesai | I78: -126.04236 | J78: https://drive.google.com/file/d/1mt1lNf5USb04qd1uinc6E6zA0raMupvO/view?usp=drivesdk
A79: Tugas | B79: Komunikasi | C79: 45844.587 | D79: 45847.5 | E79: EKA ADHIKARA RAHIM | F79: tugas merangkum video sesuai PPT link video : https://www.youtube.com/watch?v=m0GzD8fZr70 format penamaan: 4-4_absen_nama_tugas rangkuman video | G79: a0cf3905-5a36-4f5c-b02b-0b8753a1503c | H79: Lewat/Selesai | I79: -125.5 | J79: https://drive.google.com/file/d/1hvvqBjRnpF2HxTbed_VduOUyoi2g_6Lu/view?usp=drivesdk
A80: Pengingat | B80: Upacara Bendera | C80: 45844.811 | D80: 45845.26 | F80: Jangan hanya mantan aja yang kita kenang, tapi para pahlawan juga wajib kita kenang. Ayo kita Upacara. | G80: 7375edba-6d6d-40dd-9bb2-6d29eb669dd3 | H80: Lewat/Selesai | I80: -127.73958
A81: Pengingat | B81: Olahraga Bareng | C81: 45844.811 | D81: 45845.663 | F81: Kamu tahu ngga kenapa diadakan olahraga bareng? Agar kita dapat berkeringat bareng. | G81: 4a78d1de-3192-4e6c-9849-37d3bea473ab | H81: Lewat/Selesai | I81: -127.33681 | J81: https://drive.google.com/file/d/1Y0V-K2RcUNoQsFkgHgfiDnYoQnMzHejD/view?usp=drivesdk
A82: Tugas | B82: Pelajari masteri PI, kasus mandalika | C82: 45844.925 | D82: 45846.583 | E82: QURROTU A'YUMINA | F82: Kasus Mandalika: Apakah sudah ditetapkan menjadi BUT? Jika ya/tidak, apa alasannya? Bagi yang punya kenalan, minta tolong tanyakan ke KPP Pratama Praya (terima kasih) Pelajari materi kondisi PE berkaitan dengan subsidiary. 10.1. Ketepatan menjelaskan konsep laba usaha; 10.2. Ketepatan menjelaskan cakupan laba usaha yang dapat dipajaki di negara lokasi BUT; 10.3. Ketepatan menjelaskan penentuan laba BUT berdasarkan artibusi faktual; 10.4. Ketepatan menjelaskan ketentuan khusus bagi penghasilan dari pengangkutan laut dan udara. materi terlampir Reminder: kemungkinan PI sama seperti pertemuan sebelumnya, No gadget, laptop, dll. Jadi untuk persiapan kelas bisa siapkan catatan/print materi, atau yang lain yang bisa digunakan untuk mendukung pembelajaran di kelas. | G82: 1ba403fa-afc6-4616-ab14-46a17523759c | H82: Lewat/Selesai | I82: -126.41667 | J82: https://drive.google.com/file/d/1ufLBF4qi9nNjiyO4Vhhuvjqgm-1uBnZM/view?usp=drivesdk
A83: Pengingat | B83: Apel Pagi | C83: 45845.926 | D83: 45846.26 | F83: 🟢 Apel Nonasrama 🟢 1. Sarjana Terapan (Alih Program) Semester 8 2. D-III semester 4 📆 Selasa, 8 Juli 2025 🕢 06.30 s.d. 07.00 WIB 🏛 Lapangan A (Ged. G digunakan apabila kondisi hujan) 🎙 Akhmad Priharjanto (Plt Kepala Program Studi Akuntansi Sektor Publik) Mahasiswa hadir dan siap di barisan pukul 06.15 WIB tepat. Setiap kelas mendokumentasikan kehadiran dan disampaikan kepada UPK maksimal pada pukul 20.00 sesuai ketentuan pada tautan: bit.ly/rekapkegiatanrutin Terima kasih. | G83: 50c8b79e-8a9f-4faa-b52c-820cd1bace79 | H83: Lewat/Selesai | I83: -126.73958
A84: Tugas | B84: AKSK Individu | C84: 45846.357 | D84: 45850.749 | E84: ANISA FATMANINGTYAS | F84: Tugas Individu ke-10 - Resume materi Arens Bab 17, 18, 20 Ketentuan resume : - 3 Bab itu dijadiin 1 resume ya, maks 2 halaman folio - Ditulis tangan di kertas ukuran folio (buku/kertas) ⚠ Pengumpulan: https://bit.ly/44_AKSK 📅 Deadline: Sabtu, 12 Juli 2025 sebelum pukul 18.00 WIB | G84: cfb58659-df4b-40c7-a956-ea75b0ee02c2 | H84: Lewat/Selesai | I84: -122.25069
A85: Tugas | B85: AKSK Kelompok | C85: 45846.358 | D85: 45850.749 | E85: DEA LESTI BRIANA | F85: TUGAS KELOMPOK Tugas ke-9: Reviu ICQ Modul 2 (tabel buku 1 hal 46); Tugas ke-10: Reviu ICQ Modul 3(tabel buku 1 hal 78); Ketentuan Reviu ICQ: bagaimana potensi mistatement nya (yg jawaban kuesionernya tidak), apa kelebihan dan kelemahan pengendaliannya, apa saja langkah audit untuk cek dan uji kelebihan dan kelemahan tsb Tambahan: Kelompok 3 presentasi modul 3 ⚠ Pengumpulan: https://bit.ly/44_AKSK 📅 Deadline: Sabtu, 12 Juli 2025 sebelum pukul 18.00 WIB | G85: b4a45694-a8ca-4a1c-8f43-b499eff88685 | H85: Lewat/Selesai | I85: -122.25069
A86: Tugas | B86: Tugas ADP KE 5 Time Series | C86: 45847.344 | D86: 45852.958 | E86: AHMAD NUR WAKHID | F86: 🚨🚨TUGAS ANALITIKA DATA PERPAJAKAN🚨🚨 Berikut pengumuman terkait Tugas Kelompok mata kuliah Analitika Data Perpajakan: - Tugas Ke 5 (Pertemuan 9-10) Time Series, Deadline Senin, 14 Juli 2025 23.59 WIB Data yang dianalisis: - Bisa berupa data non-perpajakan, namun disarankan menggunakan data perpajakan untuk hasil yang lebih relevan (Nilai tugas akan lebih tinggi jika menggunakan data perpajakan dan jumlah baris data lebih dari 500 baris). - Boleh menggunakan data sebelumnya (Tugas 1) atau bisa pake data baru Kerahasiaan Data: - Jika data mengandung informasi rahasia (Nama Wajib Pajak, NPWP, dll.), wajib disamarkan untuk menjaga privasi. Format Laporan: a. Permasalahan b. Eksplorasi Data c. Pemilihan Model d. Hasil e. Evaluasi model f. Interpretasi hasil g. Kesimpulan Referensi dapat dilihat di Folder Pak Galela Pertemuan 9-10 (https://drive.google.com/drive/folders/1cVmRp7obwl7gm8WepPYv6xOh9jcjHxYV?usp=drive_link) Format Penamaan File Tugas: 1. Data Excel: (.xlsx atau .csv) contoh: 4-4_Kelompok 1_Tugas Ke-5 Time Series_Pertemuan 9-10.xlsx 2. File Orange: (.ows) contoh: 4-4_Kelompok 1_Tugas Ke-5 Time Series_Pertemuan 9-10.ows 3. Laporan Hasil Analisis: (.pdf) contoh: 4-4_Kelompok 1_Tugas Ke-5 Time Series_Pertemuan 9-10.pdf (Tidak perlu di zip, langsung diupload di folder kelompok masing-masing) 📍Link Pengumpulan Tugas: [Link Pengumpulan Tugas: https://drive.google.com/open?id=1DkQP4AZWubhDITHd1ZXpblnrrWJ81G-5&usp=drive_fs ] | G86: 5260580b-f9c3-496d-82b7-df3b8844e39c | H86: Lewat/Selesai | I86: -120.04236 | J86: https://drive.google.com/file/d/1IaT9VfwrzD8CrlXZP_JnHhg1zCMrCVS_/view?usp=drivesdk
A87: Tugas | B87: Tugas AKM II | C87: 45849.848 | D87: 45853.958 | E87: ZETA TALADZUL AYUN | F87: ✨Tugas AKM II✨ 1️⃣ Tugas Individu 1.⁠ ⁠Penyelesaian soal (ditulis tangan) 2.⁠ ⁠⁠Membuat Kerangka materi / infografis (ringkas dan komprehensif, dalam bentuk gambar dan kata kunci) (tulis tangan, cukup 1 halaman, boleh lebih) di buku B5 dapat melanjutkan dr buku AKM I 3. Materi tentang Akuntansi Syariah ditulis penertiannya dan perbedaannya dengan yang konvensional saja tidak sampai contoh soal/kasusnya. Utk bab 20, jawaban soal CA merupakan bagian dari ringkasan 2️⃣ Tugas Presentasi Presensi 11 (melanjutkan presentasi sebelumnya) Presensi 12 s.d. 23 (Soal Pertemuan 11) Perhatikan detil instruksi pengerjaan per masing-masing soal yang ada pada pdf tugas ‼️ 📌 Urutan pengerjaan •⁠ ⁠Pokok Materi •⁠ ⁠⁠Referensi, halaman, dan penjelasan (infografis, ringkas dan komprehensif, dalam bentuk bagan, tabel, dan kata kunci) •⁠ ⁠⁠Soal, data singkat, subpertanyaan, jawaban (disertai data yang diperlukan, penjelasan langkah-langkah pengerjaan soal, hitungan) •⁠ ⁠⁠Setiap subpertanyaan langsung disandingkan dengan jawaban •⁠ ⁠⁠Jumlah slide sesedikit mungkin 📌 Format file Word atau Excel dan PPT 📌 nama file: No. Presensi_Nama Mahasiswa_No Soal_Jenis Materi 🗓️ Selasa, 15 Juli 2025 📍 LMS dan gdrive https://drive.google.com/drive/folders/1EfxeoDokR5GHJIEZU3oWr2AlEPJGT_L_ 🤺🤺🤺🤺 | G87: b46be921-e26e-4e19-ac92-14bb395aec5c | H87: Lewat/Selesai | I87: -119.04236 | J87: https://drive.google.com/file/d/10Ojx9zJYPVbeGT9SsQ8ytG_SPDemQkye/view?usp=drivesdk
A88: Tugas | B88: Tugas KomPer: Feature dan Opini | C88: 45850.654 | D88: 45854.958 | E88: EKA ADHIKARA RAHIM | F88: Carilah 1 tulisan berjenis feature dan 1 tulisan berjenis opini! | G88: ddf29cbf-de20-4bfd-81c5-a4d6eef88e2c | H88: Lewat/Selesai | I88: -118.04236
A89: Tugas | B89: Tugas KomPer: Membuat Opini | C89: 45850.655 | D89: 45854.958 | E89: EKA ADHIKARA RAHIM | F89: Buatlah artikel opini tentang isu perpajakan! di PPT ada cara penulisan Opini yang baik | G89: 175ba0c1-642c-4ff3-b04c-018b7bdae22d | H89: Lewat/Selesai | I89: -118.04236 | J89: https://drive.google.com/file/d/1ZvCAnI7FZNladdFXkqZ8h51npxD0GFBw/view?usp=drivesdk
A90: Pengingat | B90: Olahraga Bareng | C90: 45852.815 | D90: 45852.663 | F90: Kamu tahu ngga kenapa diadakan olahraga bareng? Agar kita dapat berkeringat bareng. | G90: d059e340-76f9-468c-9361-972370af59a6 | H90: Lewat/Selesai | I90: -120.33681 | J90: https://drive.google.com/file/d/1Nl4YakgsTMVEqErx79TYAb9FOlwY2biR/view?usp=drivesdk
A91: Pengingat | B91: Apel Pagi | C91: 45852.815 | D91: 45853.26 | F91: Apel Pagi aja aku datengin, masa kamu ngga aku apelin. | G91: fd8a54c0-6367-40bd-92af-0b3afa6fe6fd | H91: Lewat/Selesai | I91: -119.73958
A93: Tugas | B93: Pajak Internasional | C93: 45853.446 | D93: 45867.583 | E93: QURROTU A'YUMINA | F93: Pertemuan ke 3 setelah uts (pertemuan ke 11) SIlahkan dipelajari guys, bisa baca dari ddtc juga. Terima kasih, semoga dipermudah memahami materinya ya 🫶🩵 | G93: 630a6576-8f53-4ca6-8b0b-4f7ce3330d71 | H93: Lewat/Selesai | I93: -105.41667 | J93: https://drive.google.com/file/d/1sU8oC5s_zzx1BHMT8RjcoDilWXo2Eks0/view?usp=drivesdk
A94: Tugas | B94: Pajak Internasional | C94: 45853.446 | D94: 45860.583 | E94: QURROTU A'YUMINA | F94: Pelajari materi 9, 10 Pajak Internasional File yg materi 9 gabung sama 8 kemarin | G94: 1592fab7-536f-4586-8b37-f60623bcde8a | H94: Lewat/Selesai | I94: -112.41667 | J94: https://drive.google.com/file/d/1jmb7-dwehPKWSLWqHijjdQHB1InFGeAo/view?usp=drivesdk
A95: Tugas | B95: AKSK KELOMPOK | C95: 45853.537 | D95: 45857.749 | E95: ANISA FATMANINGTYAS | F95: TUGAS AKSK KELOMPOK: -tugas kelompok-11 submit modul 1 update modul 3 -tugas kelompok-12 modul 5 semua submit -tugas kelompok-13 modul 6 semua submit -kel 4 maju modul 5 -kel 5 maju modul 6 Submit di gform seperti biasa sebelum 18.00 WIB | G95: e9d6f7b9-7a6e-4e9f-8027-b66ee29aa560 | H95: Lewat/Selesai | I95: -115.25069
A96: Tugas | B96: Tugas ADP Ke 6 | C96: 45856.369 | D96: 45859.958 | E96: AHMAD NUR WAKHID | F96: 🚨🚨TUGAS ANALITIKA DATA PERPAJAKAN🚨🚨 Berikut pengumuman terkait Tugas Kelompok mata kuliah Analitika Data Perpajakan: - Tugas Ke 5 (Pertemuan 11) Asosiasi, Deadline Senin, 21 Juli 2025 23.59 WIB Data yang dianalisis: - Bisa berupa data non-perpajakan, namun disarankan menggunakan data perpajakan untuk hasil yang lebih relevan (Nilai tugas akan lebih tinggi jika menggunakan data perpajakan dan jumlah baris data lebih dari 500 baris). - Boleh menggunakan data sebelumnya (Tugas 1) atau bisa pake data baru Kerahasiaan Data: - Jika data mengandung informasi rahasia (Nama Wajib Pajak, NPWP, dll.), wajib disamarkan untuk menjaga privasi. Format Laporan: a. Permasalahan b. Eksplorasi Data c. Pemilihan Model d. Hasil e. Evaluasi model f. Interpretasi hasil g. Kesimpulan Referensi dapat dilihat di Folder Pak Galela Pertemuan 8 (https://drive.google.com/drive/folders/1dYOSvU9FEoax99W7a495CPq4pIVNl-nb?usp=drive_link) Format Penamaan File Tugas: 1. Data Excel: (.xlsx atau .csv) contoh: 4-4_Kelompok 1_Tugas Ke-6 Asosiasi_Pertemuan 11.xlsx 2. File Orange: (.ows) contoh: 4-4_Kelompok 1_Tugas Ke-6 Asosiasi_Pertemuan 11.ows 3. Laporan Hasil Analisis: (.pdf) contoh: 4-4_Kelompok 1_Tugas Ke-6 Asosiasi_Pertemuan 11.pdf (Tidak perlu di zip, langsung diupload di folder kelompok masing-masing) 📍Link Pengumpulan Tugas: [Link Pengumpulan Tugas: https://drive.google.com/open?id=1DkQP4AZWubhDITHd1ZXpblnrrWJ81G-5&usp=drive_fs ] | G96: 4d0d9946-54ca-4332-aeb9-bf5048131677 | H96: Lewat/Selesai | I96: -113.04236
A97: Tugas | B97: Tugas AKM II | C97: 45857.628 | D97: 45860.958 | E97: ZETA TALADZUL AYUN | F97: ✨Tugas AKM II✨ 1️⃣ Tugas Individu 1.⁠ ⁠Penyelesaian soal (ditulis tangan) 2.⁠ ⁠⁠Membuat Kerangka materi / infografis (ringkas dan komprehensif, dalam bentuk gambar dan kata kunci) (tulis tangan, cukup 1 halaman, boleh lebih) di buku B5 dapat melanjutkan dr buku AKM I 3. Materi tentang Akuntansi Syariah ditulis pengertiannya dan perbedaannya dengan yang konvensional, soal jawab jadinya juga ditulis ya, data soal bisa diringkas. Utk bab 20, jawaban soal CA merupakan bagian dari ringkasan 2️⃣ Tugas Presentasi Presensi 17 s.d. 23 (melanjutkan presentasi sebelumnya) Presensi 24 (Soal Pertemuan 12) Perhatikan detil instruksi pengerjaan per masing-masing soal yang ada pada pdf tugas ‼️ 📌 Urutan pengerjaan •⁠ ⁠Pokok Materi •⁠ ⁠⁠Referensi, halaman, dan penjelasan (infografis, ringkas dan komprehensif, dalam bentuk bagan, tabel, dan kata kunci) •⁠ ⁠⁠Soal, data singkat, subpertanyaan, jawaban (disertai data yang diperlukan, penjelasan langkah-langkah pengerjaan soal, hitungan) •⁠ ⁠⁠Setiap subpertanyaan langsung disandingkan dengan jawaban •⁠ ⁠⁠Jumlah slide sesedikit mungkin 📌 Format file Word atau Excel dan PPT 📌 nama file: No. Presensi_Nama Mahasiswa_No Soal_Jenis Materi 🗓️ Selasa, 22 Juli 2025 📍 LMS dan gdrive https://drive.google.com/drive/folders/1EfxeoDokR5GHJIEZU3oWr2AlEPJGT_L_ 🤺🤺🤺🤺 | G97: 287288b4-f963-4b02-925c-b3f73429bfb5 | H97: Lewat/Selesai | I97: -112.04236 | J97: https://drive.google.com/file/d/1w4G_yh3dbns6Kg6gA2BYuT9FGermGzwQ/view?usp=drivesdk
A98: Tugas | B98: Tugas Profil WP | C98: 45858.866 | D98: 45874.958 | E98: EVI SETYANINGSIH | F98: Susunlah Profil WP berdasarkan data di LMS ke dalam bentuk PPT. Pembagian kelompok ada di lampiran Jaga-jaga ibunya minta presentasi lebih awal | G98: 4d4b630c-1538-4d10-993e-920a81a73b1c | H98: Lewat/Selesai | I98: -98.042361 | J98: https://drive.google.com/file/d/178uzdOo7u5r5HAuYBrEe35xJk5YwEUeQ/view?usp=drivesdk
A99: Pengingat | B99: Upacara Bendera | C99: 45859.538 | D99: 45859.26 | F99: Jangan hanya mantan aja yang kita kenang, tapi para pahlawan juga wajib kita kenang. Ayo kita Upacara. | G99: 6a84bd32-6c57-4eb0-aaa7-147b214bf072 | H99: Lewat/Selesai | I99: -113.73958
A100: Pengingat | B100: Olahraga Bareng | C100: 45859.539 | D100: 45859.663 | F100: Kamu tahu ngga kenapa diadakan olahraga bareng? Agar kita dapat berkeringat bareng. | G100: 1d4887c4-152e-4050-a2b0-9194b460355a | H100: Lewat/Selesai | I100: -113.33681 | J100: https://drive.google.com/file/d/1hgKB2AowjvT57wNQXQ9u7-MsL5OmrRXT/view?usp=drivesdk
A101: Pengingat | B101: Apel Pagi | C101: 45859.83 | D101: 45860.26 | F101: Apel Pagi aja aku datengin, masa kamu ngga aku apelin. | G101: 75e3f987-c4c8-48d7-ba80-e6f14197f644 | H101: Lewat/Selesai | I101: -112.73958
A102: Tugas | B102: AKSK KELOMPOK | C102: 45859.911 | D102: 45864.749 | E102: ANISA FATMANINGTYAS | F102: TUGAS KELOMPOK: - tugas kelompok-14 mereviu ICQ modul 7 - tugas kelompok-15 mereviu ICQ modul 8 Ketentuan Reviu ICQ: bagaimana potensi mistatement nya (yg jawaban kuesionernya tidak), apa kelebihan dan kelemahan pengendaliannya, apa saja langkah audit untuk cek dan uji kelebihan dan kelemahan tsb - tugas kelompok-16 mengerjakan modul 7 - tugas kelompok-17 mengerjakan modul 8 Tambahan: - kelompok 6 maju modul 7 - kelompok 7 maju modul 8 Pengumpulan: https://bit.ly/44_AKSK | G102: 82bd0f60-a0c8-49a0-892c-1896970eece3 | H102: Lewat/Selesai | I102: -108.25069
A103: Tugas | B103: AKSK INDIVIDU | C103: 45859.912 | D103: 45864.749 | E103: DEA LESTI BRIANA | F103: TUGAS INDIVIDU: tugas individu-11: buat resume bab 19 dan 21 arens (2 bab dijadiin 1 rangkuman, maks 2 halaman) Pengumpulan: https://bit.ly/44_AKSK | G103: 42e72354-0757-4d4e-8c62-afc4261bc3c5 | H103: Lewat/Selesai | I103: -108.25069
A104: Tugas | B104: Tugas Komper: Edukasi Perpajakan | C104: 45861.455 | D104: 45875.958 | E104: EKA ADHIKARA RAHIM | F104: di upload di LMS pertemuan 6 | G104: a3bfc159-ac2a-43c1-bc54-f522f5e73ea9 | H104: Lewat/Selesai | I104: -97.042361 | J104: https://drive.google.com/file/d/1LRNo2MwzN6x-UUrf6OJ8dplh8Hwgjuyq/view?usp=drivesdk
A105: Tugas | B105: Tugas AKM II | C105: 45862.46 | D105: 45867.958 | E105: ZETA TALADZUL AYUN | F105: ✨Tugas AKM II✨ 1️⃣ Tugas Individu 1.⁠ ⁠Penyelesaian soal (ditulis tangan) 2.⁠ ⁠⁠Membuat Kerangka materi / infografis (ringkas dan komprehensif, dalam bentuk gambar dan kata kunci) (tulis tangan, cukup 1 halaman, boleh lebih) di buku B5 dapat melanjutkan dr buku AKM I 3. Materi tentang Akuntansi Syariah ditulis pengertiannya dan perbedaannya dengan yang konvensional, soal jawab jadinya juga ditulis ya, data soal bisa diringkas. Utk bab 20, jawaban soal CA merupakan bagian dari ringkasan 2️⃣ Tugas Presentasi Presensi 24 (melanjutkan presentasi sebelumnya) Presensi 25 s.d. 4 (Soal Pertemuan 13) Perhatikan detil instruksi pengerjaan per masing-masing soal yang ada pada pdf tugas ‼️ *TERDAPAT REVISI PDF TUGAS PRESENTASI (REV2) 📌 Urutan pengerjaan •⁠ ⁠Pokok Materi •⁠ ⁠⁠Referensi, halaman, dan penjelasan (infografis, ringkas dan komprehensif, dalam bentuk bagan, tabel, dan kata kunci) •⁠ ⁠⁠Soal, data singkat, subpertanyaan, jawaban (disertai data yang diperlukan, penjelasan langkah-langkah pengerjaan soal, hitungan) •⁠ ⁠⁠Setiap subpertanyaan langsung disandingkan dengan jawaban •⁠ ⁠⁠Jumlah slide sesedikit mungkin 📌 Format file Word atau Excel dan PPT 📌 nama file: No. Presensi_Nama Mahasiswa_No Soal_Jenis Materi 🗓️ Selasa, 29 Juli 2025 📍 LMS dan gdrive https://drive.google.com/drive/folders/1EfxeoDokR5GHJIEZU3oWr2AlEPJGT_L_ 🤺🤺🤺🤺 | G105: a4b4156d-84fd-4470-aa30-1c44c401d402 | H105: Lewat/Selesai | I105: -105.04236 | J105: https://drive.google.com/file/d/15g9jp5wqMUcNm28hS6h1i7j3T0lv4pob/view?usp=drivesdk
A106: Pengingat | B106: Apel Pagi | C106: 45866.681 | D106: 45867.26 | F106: Apel Pagi aja aku datengin, masa kamu ngga aku apelin. | G106: 6320398a-f3b5-479e-856b-806927ebd038 | H106: Lewat/Selesai | I106: -105.73958
A107: Tugas | B107: Pajak Internasional | C107: 45867.209 | D107: 45868.583 | E107: QURROTU A'YUMINA | F107: PI pertemuan ke 4 setelah UTS (pertemuan 12) Materi: Pemajakan passive income terlampir | G107: a41529cf-1068-4591-b666-9b4c32d55d9a | H107: Lewat/Selesai | I107: -104.41667 | J107: https://drive.google.com/file/d/11VJInXeds-KZ4PXGFaYIs_9JNkAeeORy/view?usp=drivesdk
A108: Tugas | B108: AKSK INDIVIDU | C108: 45867.813 | D108: 45871.749 | E108: DEA LESTI BRIANA | F108: TUGAS INDIVIDU: tugas individu-12: buat resume bab 22 arens tulis tangan (maks 2 halaman folio) Tugas individu-13: tulis tangan buku 2 dari modul 1 sd modul 8. karena kita pernah nulis modul 1-3, tar di merge aja sama modul 4-8, jadiin 1 file. Pengumpulan: https://bit.ly/44_AKSK | G108: 4e8dfafe-09e6-47a8-baef-b3d479d902c6 | H108: Lewat/Selesai | I108: -101.25069
A109: Tugas | B109: AKSK KELOMPOK | C109: 45867.815 | D109: 45871.749 | E109: ANISA FATMANINGTYAS | F109: TUGAS KELOMPOK: - tugas kelompok-18 mereviu ICQ modul 4 - tugas kelompok-19 mengerjakan modul 4 Ketentuan Reviu ICQ: bagaimana potensi mistatement nya (yg jawaban kuesionernya tidak), apa kelebihan dan kelemahan pengendaliannya, apa saja langkah audit untuk cek dan uji kelebihan dan kelemahan tsb Tambahan: - kelompok 1 maju modul 4 Pengumpulan: https://bit.ly/44_AKSK | G109: f220b88f-adbc-477c-a340-c3ea33d0c986 | H109: Lewat/Selesai | I109: -101.25069
A110: Tugas | B110: Presentasi Mankeu | C110: 45869.752 | D110: 45873.312 | E110: YOHANA ESTERINDAH SIMANJUNTAK | F110: ❗MANKEU❗pertemuan 12 : Bab 17 Peramalan dan Perencanaan Keuangan 1. kalo bisa jelasin minimal spt video bapaknya di https://www.youtube.com/watch?v=rWdRDEeDu10&list=PLRNfI9HLyZb8E4EWPl5NApDzkr7QfQwJH&index=17 2. ⁠paham dan menguasai materi sampe ke inti2nya di tiap slide 3. ⁠awal ngomong jgn hah hoh hah hoh, harus terlihat paham. karena kalo tau awal2 udah kebingungan pasti ga belajar 4. ⁠usahain pas menjelaskan materi maks 8-10 menit, kalo dah 4 menit dah aman sebenernya 5. ⁠boleh buka PPT, notes, hp ke depan 6. ⁠usahain belajar PPT bapaknya dulu baru zoom untuk diskusi bareng2 sama kelompoknya masing2 | G110: bc7950a7-8ea0-4925-b872-27b4c948ab42 | H110: Lewat/Selesai | I110: -99.6875
A111: Tugas | B111: Tugas ADP ke 7 | C111: 45869.958 | D111: 45873.958 | E111: AHMAD NUR WAKHID | F111: 🚨🚨TUGAS ANALITIKA DATA PERPAJAKAN🚨🚨 Berikut pengumuman terkait Tugas Kelompok mata kuliah Analitika Data Perpajakan: - Tugas Ke 7 (Pertemuan 13) Data Teks, Deadline Senin, 4 Agustus 2025 23.59 WIB Data yang dianalisis: - Data berbentuk teks (saran pake data Putusan dari bapaknya (ada di folder pertemuan 11 dan 12) Kerahasiaan Data: - Jika data mengandung informasi rahasia (Nama Wajib Pajak, NPWP, dll.), wajib disamarkan untuk menjaga privasi. Format Laporan: a. Permasalahan b. Eksplorasi Data c. Pemilihan Model d. Hasil e. Evaluasi model f. Interpretasi hasil g. Kesimpulan Format Penamaan File Tugas: 1. Data Excel: (.xlsx atau .csv) contoh: 4-4_Kelompok 1_Tugas Ke-7 Data Teks_Pertemuan 13.xlsx 02. File Orange: (.ows) contoh: 4-4_Kelompok 1_Tugas Ke-7 Data Teks_Pertemuan 13.ows 3. Laporan Hasil Analisis: (.pdf) contoh: 4-4_Kelompok 1_Tugas Ke-7 Data Teks_Pertemuan 13.pdf (Tidak perlu di zip, langsung diupload di folder kelompok masing-masing) 📍Link Pengumpulan Tugas: [Link Pengumpulan Tugas: https://drive.google.com/open?id=1DkQP4AZWubhDITHd1ZXpblnrrWJ81G-5&usp=drive_fs ] | G111: a3801f48-88d6-45b0-bf69-8d3b6c15c128 | H111: Lewat/Selesai | I111: -99.042361
A112: Pengingat | B112: Olahraga Umum | C112: 45870.289 | D112: 45875.663 | F112: Olahraga Umum: Lapangan A | G112: 31e8e22d-e9c0-4afa-841e-db902859a1a4 | H112: Lewat/Selesai | I112: -97.336806 | J112: https://drive.google.com/file/d/1ytciiRlIS-9lctlbE1XdKwGeIlkoweuy/view?usp=drivesdk
A113: Tugas | B113: Tugas AKM II | C113: 45872.537 | D113: 45874.958 | E113: ZETA TALADZUL AYUN | F113: ✨Tugas AKM II✨ 1️⃣ Tugas Individu 1.⁠ ⁠Penyelesaian soal (ditulis tangan) 2.⁠ ⁠⁠Membuat Kerangka materi / infografis (ringkas dan komprehensif, dalam bentuk gambar dan kata kunci) (tulis tangan, cukup 1 halaman, boleh lebih) di buku B5 dapat melanjutkan dr buku AKM I 3. Materi tentang Akuntansi Syariah ditulis pengertiannya dan perbedaannya dengan yang konvensional, soal jawab jadinya juga ditulis ya, data soal bisa diringkas. Utk bab 20, jawaban soal CA merupakan bagian dari ringkasan 2️⃣ Tugas Presentasi Presensi 1 s.d. 4 (melanjutkan presentasi sebelumnya) Presensi 5 s.d. 17 (Soal Pertemuan 14) Perhatikan detil instruksi pengerjaan per masing-masing soal yang ada pada pdf tugas ‼️ 📌 Urutan pengerjaan •⁠ ⁠Pokok Materi •⁠ ⁠⁠Referensi, halaman, dan penjelasan (infografis, ringkas dan komprehensif, dalam bentuk bagan, tabel, dan kata kunci) •⁠ ⁠⁠Soal, data singkat, subpertanyaan, jawaban (disertai data yang diperlukan, penjelasan langkah-langkah pengerjaan soal, hitungan) •⁠ ⁠⁠Setiap subpertanyaan langsung disandingkan dengan jawaban •⁠ ⁠⁠Jumlah slide sesedikit mungkin 📌 Format file Word atau Excel dan PPT 📌 nama file: No. Presensi_Nama Mahasiswa_No Soal_Jenis Materi 🗓️ Selasa, 5 Agustus 2025 📍 LMS dan gdrive https://drive.google.com/drive/folders/1EfxeoDokR5GHJIEZU3oWr2AlEPJGT_L_ 🤺🤺🤺🤺 | G113: 0e5eb74f-578e-4ad4-8c93-01ec39b5c887 | H113: Lewat/Selesai | I113: -98.042361 | J113: https://drive.google.com/file/d/1KCcLP1SxChaqin55X2f93kQFsDemZAp1/view?usp=drivesdk
A114: Tugas | B114: Tugas Profil WP | C114: 45872.602 | D114: 45881.958 | E114: EVI SETYANINGSIH | F114: Susunlah Profil WP berdasarkan data di LMS ke dalam bentuk PPT. Pembagian kelompok ada di lampiran | G114: ce0242b0-33e6-4a3e-81ce-071c8261054a | H114: Lewat/Selesai | I114: -91.042361 | J114: https://drive.google.com/file/d/1QAwHxz4D6Lij5ZUZ_veZbTvgw30i0itG/view?usp=drivesdk
A115: Pengingat | B115: Upacara | C115: 45872.708 | D115: 45873.271 | F115: 📢 PENGUMUMAN 📢 Pelaksanaan Upacara Bendera Senin, 4 Agustus 2025 ⏰ Waktu: Pukul 06.30 WIB 🏛Tempat: Lapangan A 🎙 Inspektur Upacara Sekretaris Program Studi Diploma III Kebendaharaan Negara 👔 Dresscode: Seragam Kuliah Senin dan Topi PKN STAN (bagi yg memiliki) 👤 Peserta Upacara: - Mahasiswa D-III semester 4 dan 6 (termasuk BL) - Mahasiswa S.Tr AP semester 8 Mahasiswa hadir dan siap di barisan pukul 06.15 tepat. Setiap kelas wajib mendokumentasikan, mendata kehadiran, dan melaporkan kepada UPK maksimal pada pukul 20.00 di tautan: https://bit.ly/rekapkegiatanrutin | G115: a0fbf711-4fc9-4c50-83c6-1f2db63a0eb9 | H115: Lewat/Selesai | I115: -99.729167 | J115: https://drive.google.com/file/d/1PqdNW-z_6fyYbVl06DxLo-_OY8SxOO5e/view?usp=drivesdk
A116: Tugas | B116: AKSK INDIVIDU | C116: 45873.463 | D116: 45878.749 | E116: ANISA FATMANINGTYAS | F116: TUGAS INDIVIDU: - tugas individu-14: buat resume bab 23 arens tulis tangan (maks 2 halaman folio) Pengumpulan: https://bit.ly/44_AKSK | G116: d54e6eb2-2241-4fb0-8327-d9ab35004472 | H116: Lewat/Selesai | I116: -94.250694
...

Sheet Anggota
A1: Kelas 3-04
A3: No | B3: NIM | C3: Nama | D3: ultah tahun ini | E3: Nama Kos | F3: Alamat Kos/Kontrakan/Apartemen/Mansion/Villa | G3: Nomor Kontak Darurat (Orangtua) | H3: Nomor ibu/bapak kos
A4: 1 | B4: 3032240040 | C4: AHMAD NUR WAKHID | D4: =VLOOKUP(C4,'data d3'!C:L,10,0) -> 45797
A5: 2 | B5: 3032240016 | C5: ANISA FATMANINGTYAS | D5: =VLOOKUP(C5,'data d3'!C:L,10,0) -> 45892
A6: 3 | B6: 3032240008 | C6: ANNISA FADILLAH HERNAWAN | D6: =VLOOKUP(C6,'data d3'!C:L,10,0) -> 45740
A7: 4 | B7: 3032240030 | C7: ARRAZ MEIDYAN | D7: =VLOOKUP(C7,'data d3'!C:L,10,0) -> 45801 | E7: rumah | F7: Jl Raden Sanim No. 12, Tanah Baru, Beji, Depok | G7: 082111642266 | H7: -
A8: 5 | B8: 3032240010 | C8: AYU MITHA VALLENTYA | D8: =VLOOKUP(C8,'data d3'!C:L,10,0) -> 45984
A9: 6 | B9: 3032240027 | C9: DEA LESTI BRIANA | D9: =VLOOKUP(C9,'data d3'!C:L,10,0) -> 45901 | E9: Cozy Kost | F9: Jl Cenderawasih I Blok A20 No 12 RT 003 RW 007, PJMI, Jurangmangu Timur, Pondok Aren | G9: 6285328734784 | H9: 087734859914
A11: 8 | B11: 3032240044 | C11: EVI SETYANINGSIH | D11: =VLOOKUP(C11,'data d3'!C:L,10,0) -> 45966 | E11: Kos Nada | F11: Komplek Griya Soegi No. 3A (rumah paling ujung sebelah kiri), Jurangmangu Timur, Pondok Aren, Tangsel
A12: 9 | B12: 3032240029 | C12: FELITA DELVIANA YOGYANTORO | D12: =VLOOKUP(C12,'data d3'!C:L,10,0) -> 45714
A13: 10 | B13: 3032240038 | C13: GIDEON HAMONANGAN SIMANJUNTAK | D13: =VLOOKUP(C13,'data d3'!C:L,10,0) -> 45784
A14: 11 | B14: 3032240018 | C14: INDAH BASUKI SETIA INDRA | D14: =VLOOKUP(C14,'data d3'!C:L,10,0) -> 45807
A15: 12 | B15: 3032240048 | C15: MARTIN FELIX SIREGAR | D15: =VLOOKUP(C15,'data d3'!C:L,10,0) -> 45810 | E15: Griya Soegi | F15: Jl. Kalimangso No.129, Jurang Manggu Tim., Kec. Pd. Aren, Kota Tangerang Selatan, Banten 15222 | G15: 85833060832 | H15: 81362111648
A16: 13 | B16: 3032240083 | C16: MELLANIA PUTRI RATNAWATI | D16: =VLOOKUP(C16,'data d3'!C:L,10,0) -> 45861
A17: 14 | B17: 3032240056 | C17: MUHAMMAD HUSNI TAMRIN | D17: =VLOOKUP(C17,'data d3'!C:L,10,0) -> 45913
A18: 15 | B18: 3032240093 | C18: MUKHLIS AHMAD ARIFIN | D18: =VLOOKUP(C18,'data d3'!C:L,10,0) -> 45845 | E18: Kos Bu Icah Suhendi | F18: Jalan Semen D2/15 Pondok Jaya | G18: 6289626394007 | H18: 6289663934015
A19: 16 | B19: 3032240066 | C19: NIDIA MUSTIKA SAPUTRA | D19: =VLOOKUP(C19,'data d3'!C:L,10,0) -> 45715
A20: 17 | B20: 3032240078 | C20: QURROTU A'YUMINA | D20: =VLOOKUP(C20,'data d3'!C:L,10,0) -> 45974 | E20: Kos PJMI | F20: Jl. Pesut Raya Blok A7 No.2, Jurang Manggu Tim., Kec. Pd. Aren, Kota Tangerang Selatan, Banten 15222 | G20: 081335247868 | H20: 6281293746097
A21: 18 | B21: 3032240071 | C21: RAHMAT RAMADHAN | D21: =VLOOKUP(C21,'data d3'!C:L,10,0) -> 46005 | E21: Kost De'Kat STAN | F21: Jl. H. Sarmili No.41a, Jurang Manggu Tim., Kec. Pd. Aren, Kota Tangerang Selatan, Banten 15222
A22: 19 | B22: 3032240094 | C22: ROBERTUS KLEMENS NOVIARTHA | D22: =VLOOKUP(C22,'data d3'!C:L,10,0) -> 45984
A23: 20 | B23: 3032240054 | C23: RUTH NOVITA MARTINA | D23: =VLOOKUP(C23,'data d3'!C:L,10,0) -> 45717 | E23: Kost Putri Rania | F23: Jln Murai no A31/14 Pondok Jurang Mangu Indah (PJMI) Bintaro, Pondok Aren, 15222, Tangerang Selatan | G23: 085156821563 | H23: 085867710995
A24: 21 | B24: 3032240070 | C24: SHAFA INANTRI AWENANG KHARISA | D24: =VLOOKUP(C24,'data d3'!C:L,10,0) -> 45881 | E24: Cozy Kost | F24: Jl Cenderawasih I Blok A20 No 12 RT 003 RW 007, PJMI, Jurangmangu Timur, Pondok Aren | G24: 081392000800 | H24: 087734859914
A25: 22 | B25: 3032240075 | C25: TIARA MORREN TAMPUBOLON | D25: =VLOOKUP(C25,'data d3'!C:L,10,0) -> 45795
A26: 23 | B26: 3032240087 | C26: UMUL MUTHΜΑΙΝΑΗ | D26: =VLOOKUP(C26,'data d3'!C:L,10,0) -> 45738 | E26: Kos Pak Slamet | F26: Jl. Makadam Blok E4 No.14, Pondok jaya | G26: 6281548670691 | H26: 81320420429
A27: 24 | B27: 3032240047 | C27: WAHYU NURSYAM PUTRA PRATAMA | D27: =VLOOKUP(C27,'data d3'!C:L,10,0) -> 45794 | E27: Griya Soegi | F27: Jl. Kalimangso No.129, Jurang Manggu Tim., Kec. Pd. Aren, Kota Tangerang Selatan, Banten 15222 | G27: 85833060832 | H27: 81362111648
A28: 25 | B28: 3032240055 | C28: YOHANA ESTERINDAH SIMANJUNTAK | D28: =VLOOKUP(C28,'data d3'!C:L,10,0) -> 45661 | E28: Rania Kos | F28: Jln Murai no A31/14 Pondok Jurang Mangu Indah (PJMI) Bintaro, Pondok Aren, 15222, Tangerang Selatan | G28: 085382849800 | H28: 085867710995
A29: 26 | B29: 3032240057 | C29: ZAHARA AFRA AL HAMBRA | D29: =VLOOKUP(C29,'data d3'!C:L,10,0) -> 45966 | E29: The Mahanipuna 90 | F29: Jl. Gapura Menteng No.90, Pd. Ranji, Kec. Ciputat Tim., Kota Tangerang Selatan, Banten 15412 | G29: 81333512604 | H29: 85600001622
A30: 27 | B30: 3032240088 | C30: ZETA TALADZUL AYUN | D30: =VLOOKUP(C30,'data d3'!C:L,10,0) -> 45664 | E30: Kost Beton | F30: Perumahan Pondok Jaya, Jl Beton Blok C1 No 1, Pondok Ranji Ciputat Timur, Tangerang Selatan | G30: 085713108408 | H30: 087719659073

Sheet Log
A1: 45788.531 | B1: almadinaoelien@gmail.com | C1: AKSES_WEB_APP | D1: Parameter: {}, Pengguna (jika ada): Tidak ada info pengguna event
A2: 45788.531 | B2: almadinaoelien@gmail.com | C2: TAMBAH_AGENDA_SUKSES | D2: Nama: pajak interdimensional, Deadline: 15/5/2025, RowID: 07309db1-ec88-4444-8cc4-39f251aee72a
A3: 45788.532 | B3: almadinaoelien@gmail.com | C3: AKSES_WEB_APP | D3: Parameter: {}, Pengguna (jika ada): Tidak ada info pengguna event
A4: 45788.532 | B4: almadinaoelien@gmail.com | C4: AKSES_WEB_APP | D4: Parameter: {}, Pengguna (jika ada): Tidak ada info pengguna event
A5: 45789.329 | B5: almadinaoelien@gmail.com | C5: TAMBAH_AGENDA_SUKSES | D5: Nama: Ulang tahun AHMAD NUR WAKHID, Deadline: 20/5/2025, RowID: ULTAH_AHMADNURWAKHID_2025
A6: 45789.329 | B6: almadinaoelien@gmail.com | C6: TAMBAH_AGENDA_SUKSES | D6: Nama: Ulang tahun ANISA FATMANINGTYAS, Deadline: 23/8/2025, RowID: ULTAH_ANISAFATMANINGTYAS_2025
A7: 45789.329 | B7: almadinaoelien@gmail.com | C7: TAMBAH_AGENDA_SUKSES | D7: Nama: Ulang tahun ANNISA FADILLAH HERNAWAN, Deadline: 24/3/2025, RowID: ULTAH_ANNISAFADILLAHHERNAWAN_2025
A8: 45789.329 | B8: almadinaoelien@gmail.com | C8: TAMBAH_AGENDA_SUKSES | D8: Nama: Ulang tahun ARRAZ MEIDYAN, Deadline: 24/5/2025, RowID: ULTAH_ARRAZMEIDYAN_2025
A9: 45789.329 | B9: almadinaoelien@gmail.com | C9: TAMBAH_AGENDA_SUKSES | D9: Nama: Ulang tahun AYU MITHA VALLENTYA, Deadline: 23/11/2025, RowID: ULTAH_AYUMITHAVALLENTYA_2025
A10: 45789.329 | B10: almadinaoelien@gmail.com | C10: TAMBAH_AGENDA_SUKSES | D10: Nama: Ulang tahun DEA LESTI BRIANA, Deadline: 1/9/2025, RowID: ULTAH_DEALESTIBRIANA_2025
A11: 45789.329 | B11: almadinaoelien@gmail.com | C11: TAMBAH_AGENDA_SUKSES | D11: Nama: Ulang tahun EKA ADHIKARA RAHIM, Deadline: 22/7/2025, RowID: ULTAH_EKAADHIKARARAHIM_2025
A12: 45789.329 | B12: almadinaoelien@gmail.com | C12: TAMBAH_AGENDA_SUKSES | D12: Nama: Ulang tahun EVI SETYANINGSIH, Deadline: 5/11/2025, RowID: ULTAH_EVISETYANINGSIH_2025
... A60: 45789.334 | B60: almadinaoelien@gmail.com | C60: BUAT_ULTAH_SELESAI | D60: 27 pengingat ultah baru berhasil dibuat. 0 pengingat sudah ada sebelumnya. Tahun: 2025
A61: 45789.345 | B61: almadinaoelien@gmail.com
A62: 45789.347 | B62: almadinaoelien@gmail.com | C62: AKSES_WEB_APP | D62: Parameter: {}, Pengguna (jika ada): Tidak ada info pengguna event
A63: 45789.355 | B63: almadinaoelien@gmail.com | C63: AKSES_WEB_APP | D63: Parameter: {}, Pengguna (jika ada): Tidak ada info pengguna event
A64: 45789.355 | B64: almadinaoelien@gmail.com | C64: AKSES_WEB_APP | D64: Parameter: {}, Pengguna (jika ada): Tidak ada info pengguna event
A65: 45789.356 | B65: almadinaoelien@gmail.com | C65: AKSES_WEB_APP | D65: Parameter: {}, Pengguna (jika ada): Tidak ada info pengguna event
A66: 45789.359 | B66: almadinaoelien@gmail.com | C66: AKSES_WEB_APP | D66: Parameter: {}, Pengguna (jika ada): Tidak ada info pengguna event
A67: 45789.359 | B67: almadinaoelien@gmail.com | C67: HAPUS_AGENDA_SUKSES | D67: Nama: hari sama lagi, RowID: c2d5d11a-fd9d-4acf-a9b8-7318f58752ff
A68: 45789.36 | B68: almadinaoelien@gmail.com | C68: HAPUS_AGENDA_SUKSES | D68: Nama: tessss, RowID: 13b62b72-dc20-4c9e-a10c-33f5e80e89cf
A69: 45789.648 | B69: almadinaoelien@gmail.com | C69: AKSES_WEB_APP | D69: Parameter: {}, Pengguna (jika ada): Tidak ada info pengguna event
A70: 45790.704 | B70: almadinaoelien@gmail.com | C70: AKSES_WEB_APP | D70: Parameter: {}, Pengguna (jika ada): Tidak ada info pengguna event

Sheet data d3
A1: NO | B1: NO. BPS | C1: NAMA | D1: NIP | E1: PROGRAM STUDI | F1: JADWAL DAFTAR ULANG TANGGAL | G1: JADWAL DAFTAR ULANG SESI | H1: tahun | I1: bulan | J1: tanggal | K1: tanggal lahir | L1: ultah thn ini
A2: 1 | B2: 830600001 | C2: ADITYO DWI WICAKSONO | D2: 200004102019121003 | E2: DIII AKUNTANSI | F2: 45565 | G2: 1 | H2: =LEFT(D2,4) -> 2000 | I2: =MID(D2,5,2) -> 04 | J2: =MID(D2,7,2) -> 10 | K2: =DATE(H2, I2, J2) -> 36626 | L2: =DATE(2025, MONTH(K2), DAY(K2)) -> 45757
A3: 2 | B3: 830300007 | C3: AFFAN RAFI ARDIANSYAH | D3: 200007132019121001 | E3: DIII AKUNTANSI | F3: 45565 | G3: 1 | H3: =LEFT(D3,4) -> 2000 | I3: =MID(D3,5,2) -> 07 | J3: =MID(D3,7,2) -> 13 | K3: =DATE(H3, I3, J3) -> 36720 | L3: =DATE(2025, MONTH(K3), DAY(K3)) -> 45851
A4: 3 | B4: 830300001 | C4: AHMAD SAEFULAH FATAH FAUZI | D4: 200002252019121001 | E4: DIII AKUNTANSI | F4: 45565 | G4: 1 | H4: =LEFT(D4,4) -> 2000 | I4: =MID(D4,5,2) -> 02 | J4: =MID(D4,7,2) -> 25 | K4: =DATE(H4, I4, J4) -> 36581 | L4: =DATE(2025, MONTH(K4), DAY(K4)) -> 45713
A5: 4 | B5: 830100037 | C5: AINUN FATIHAH SALSABILA | D5: 200004202019122001 | E5: DIII AKUNTANSI | F5: 45565 | G5: 1 | H5: =LEFT(D5,4) -> 2000 | I5: =MID(D5,5,2) -> 04 | J5: =MID(D5,7,2) -> 20 | K5: =DATE(H5, I5, J5) -> 36636 | L5: =DATE(2025, MONTH(K5), DAY(K5)) -> 45767
A6: 5 | B6: 830700002 | C6: AMINATUS ZUHRIA | D6: 200005292019122004 | E6: DIII AKUNTANSI | F6: 45565 | G6: 1 | H6: =LEFT(D6,4) -> 2000 | I6: =MID(D6,5,2) -> 05 | J6: =MID(D6,7,2) -> 29 | K6: =DATE(H6, I6, J6) -> 36675 | L6: =DATE(2025, MONTH(K6), DAY(K6)) -> 45806
A7: 6 | B7: 830100050 | C7: ANDI STARLA AZALIA ARDITA PUTRI | D7: 200002072019122001 | E7: DIII AKUNTANSI | F7: 45565 | G7: 1 | H7: =LEFT(D7,4) -> 2000 | I7: =MID(D7,5,2) -> 02 | J7: =MID(D7,7,2) -> 07 | K7: =DATE(H7, I7, J7) -> 36563 | L7: =DATE(2025, MONTH(K7), DAY(K7)) -> 45695
A8: 7 | B8: 830100013 | C8: ANDREA MASE CORONΑΤΑΜΑ | D8: 199911292019122001 | E8: DIII AKUNTANSI | F8: 45565 | G8: 1 | H8: =LEFT(D8,4) -> 1999 | I8: =MID(D8,5,2) -> 11 | J8: =MID(D8,7,2) -> 29 | K8: =DATE(H8, I8, J8) -> 36493 | L8: =DATE(2025, MONTH(K8), DAY(K8)) -> 45990
A9: 8 | B9: 830300004 | C9: ANISA LUTHFIAH ARDA | D9: 200003232019122003 | E9: DIJL AKUNTANSI | F9: 45565 | G9: 1 | H9: =LEFT(D9,4) -> 2000 | I9: =MID(D9,5,2) -> 03 | J9: =MID(D9,7,2) -> 23 | K9: =DATE(H9, I9, J9) -> 36608 | L9: =DATE(2025, MONTH(K9), DAY(K9)) -> 45739
A10: 9 | B10: 830300009 | C10: ARDIKA NURANDA | D10: 200005212019121001 | E10: DIII AKUNTANSI | F10: 45565 | G10: 1 | H10: =LEFT(D10,4) -> 2000 | I10: =MID(D10,5,2) -> 05 | J10: =MID(D10,7,2) -> 21 | K10: =DATE(H10, I10, J10) -> 36667 | L10: =DATE(2025, MONTH(K10), DAY(K10)) -> 45798
A11: 10 | B11: 131100001 | C11: AULYA WINDI AMIRA SHABRINA | D11: 200004272019122002 | E11: DIJL AKUNTANSI | F11: 45565 | G11: 1 | H11: =LEFT(D11,4) -> 2000 | I11: =MID(D11,5,2) -> 04 | J11: =MID(D11,7,2) -> 27 | K11: =DATE(H11, I11, J11) -> 36643 | L11: =DATE(2025, MONTH(K11), DAY(K11)) -> 45774
A12: 11 | B12: 830100019 | C12: AYU ANANDA PONGKAPADANG | D12: 200009262019122002 | E12: DIII AKUNTANSI | F12: 45565 | G12: 1 | H12: =LEFT(D12,4) -> 2000 | I12: =MID(D12,5,2) -> 09 | J12: =MID(D12,7,2) -> 26 | K12: =DATE(H12, I12, J12) -> 36795 | L12: =DATE(2025, MONTH(K12), DAY(K12)) -> 45926
A13: 12 | B13: 830500003 | C13: BRILLIAN AURIGA RELIGIO | D13: 200106172019121001 | E13: DIJI AKUNTANSI | F13: 45565 | G13: 1 | H13: =LEFT(D13,4) -> 2001 | I13: =MID(D13,5,2) -> 06 | J13: =MID(D13,7,2) -> 17 | K13: =DATE(H13, I13, J13) -> 37059 | L13: =DATE(2025, MONTH(K13), DAY(K13)) -> 45825
... A287: 286 | B287: 1330300002 | C287: VIOLINA OKΚΤΑΝΙΑ | D287: 199910262019122002 | E287: DIII PBB/PENILAI | F287: 45565 | G287: 4 | H287: =LEFT(D287,4) -> 1999 | I287: =MID(D287,5,2) -> 10 | J287: =MID(D287,7,2) -> 26 | K287: =DATE(H287, I287, J287) -> 36459 | L287: =DATE(2025, MONTH(K287), DAY(K287)) -> 45956

Sheet Arsip
